{
 "alternate_names": [
  "Kevin Chapman",
  "Kevin Andrew Chapman"
 ],
 "api_path": "/artists/214052",
 "description": {
  "plain": "Kevin Andrews Chapman, commonly known by his stage name SNBRN, is an American DJ and musician from Los Angeles.\n\nHe has accumulated over 47 million plays on SoundCloud per May 2016.\n\nHe gained attention after releasing the song \u201cRaindrops\u201d featuring Kerli. In 2016 he released the song \u201cGangsta Walk\u201d which incorporates vocals by Nate Dogg; it has per May 2016 debuted on several charts."
 },
 "facebook_name": null,
 "followers_count": 3,
 "header_image_url": "https://images.genius.com/e7777c94775b993077916a20990ac857.710x710x1.png",
 "id": 214052,
 "image_url": "https://images.genius.com/e7777c94775b993077916a20990ac857.710x710x1.png",
 "instagram_name": null,
 "is_meme_verified": false,
 "is_verified": false,
 "name": "SNBRN",
 "translation_artist": false,
 "twitter_name": null,
 "url": "https://genius.com/artists/Snbrn",
 "current_user_metadata": {
  "permissions": [
   "view_activity_stream"
  ],
  "excluded_permissions": [
   "edit",
   "edit_images",
   "edit_names",
   "edit_anything",
   "merge",
   "sort_artist_songs",
   "follow",
   "view_contribution_opportunities",
   "edit_translation_artist",
   "see_short_id"
  ],
  "interactions": {
   "following": false
  }
 },
 "description_annotation": {
  "_type": "referent",
  "annotator_id": 13525277,
  "annotator_login": "Coh-Coh",
  "api_path": "/referents/7030854",
  "classification": "unreviewed",
  "fragment": "SNBRN",
  "id": 7030854,
  "is_description": true,
  "path": "/7030854/Snbrn/Snbrn",
  "range": {
   "content": "SNBRN"
  },
  "song_id": null,
  "url": "https://genius.com/7030854/Snbrn/Snbrn",
  "verified_annotator_ids": [],
  "annotatable": {
   "api_path": "/artists/214052",
   "context": null,
   "id": 214052,
   "image_url": "https://images.genius.com/e7777c94775b993077916a20990ac857.710x710x1.png",
   "link_title": "SNBRN",
   "title": "SNBRN",
   "type": "Artist",
   "url": "https://genius.com/artists/Snbrn"
  },
  "annotations": [
   {
    "api_path": "/annotations/7030854",
    "body": {
     "plain": "Kevin Andrews Chapman, commonly known by his stage name SNBRN, is an American DJ and musician from Los Angeles.\n\nHe has accumulated over 47 million plays on SoundCloud per May 2016.\n\nHe gained attention after releasing the song \u201cRaindrops\u201d featuring Kerli. In 2016 he released the song \u201cGangsta Walk\u201d which incorporates vocals by Nate Dogg; it has per May 2016 debuted on several charts."
    },
    "comment_count": 0,
    "community": true,
    "custom_preview": null,
    "has_voters": false,
    "id": 7030854,
    "pinned": false,
    "share_url": "https://genius.com/7030854",
    "source": null,
    "state": "pending",
    "url": "https://genius.com/7030854/Snbrn/Snbrn",
    "verified": false,
    "votes_total": 0,
    "current_user_metadata": {
     "permissions": [],
     "excluded_permissions": [
      "vote",
      "edit",
      "cosign",
      "uncosign",
      "destroy",
      "accept",
      "reject",
      "see_unreviewed",
      "clear_votes",
      "propose_edit_to",
      "pin_to_profile",
      "unpin_from_profile",
      "update_source",
      "edit_custom_preview",
      "create_comment"
     ],
     "interactions": {
      "cosign": false,
      "pyong": false,
      "vote": null
     },
     "iq_by_action": {}
    },
    "authors": [
     {
      "attribution": 1.0,
      "pinned_role": null,
      "user": {
       "api_path": "/users/13525277",
       "avatar": {
        "tiny": {
         "url": "https://images.genius.com/avatars/tiny/72aeea601e1da5bb56c4b75cbc89e8f2",
         "bounding_box": {
          "width": 16,
          "height": 16
         }
        },
        "thumb": {
         "url": "https://images.genius.com/avatars/thumb/72aeea601e1da5bb56c4b75cbc89e8f2",
         "bounding_box": {
          "width": 32,
          "height": 32
         }
        },
        "small": {
         "url": "https://images.genius.com/avatars/small/72aeea601e1da5bb56c4b75cbc89e8f2",
         "bounding_box": {
          "width": 100,
          "height": 100
         }
        },
        "medium": {
         "url": "https://images.genius.com/avatars/medium/72aeea601e1da5bb56c4b75cbc89e8f2",
         "bounding_box": {
          "width": 300,
          "height": 400
         }
        }
       },
       "header_image_url": "https://images.genius.com/avatars/medium/72aeea601e1da5bb56c4b75cbc89e8f2",
       "human_readable_role_for_display": "Contributor",
       "id": 13525277,
       "iq": 2738,
       "login": "Coh-Coh",
       "name": "Coh-Coh",
       "role_for_display": "contributor",
       "url": "https://genius.com/Coh-Coh",
       "current_user_metadata": {
        "permissions": [],
        "excluded_permissions": [
         "follow"
        ],
        "interactions": {
         "following": false
        }
       }
      }
     }
    ],
    "cosigned_by": [],
    "rejection_comment": null,
    "verified_by": null
   }
  ]
 },
 "user": null,
 "songs": [
  {
   "annotation_count": 5,
   "api_path": "/songs/672294",
   "artist_names": "SNBRN (Ft. Kerli)",
   "full_title": "Raindrops by\u00a0SNBRN (Ft.\u00a0Kerli)",
   "header_image_thumbnail_url": "https://images.rapgenius.com/a0b971addd5197d2d73db3d99c1d56e9.300x300x1.png",
   "header_image_url": "https://images.rapgenius.com/a0b971addd5197d2d73db3d99c1d56e9.1000x1000x1.png",
   "id": 672294,
   "language": "en",
   "lyrics_owner_id": 70148,
   "lyrics_state": "complete",
   "path": "/Snbrn-raindrops-lyrics",
   "pyongs_count": 17,
   "relationships_index_url": "https://genius.com/Snbrn-raindrops-sample",
   "release_date_components": {
    "year": 2015,
    "month": 1,
    "day": 20
   },
   "release_date_for_display": "January 20, 2015",
   "release_date_with_abbreviated_month_for_display": "Jan. 20, 2015",
   "song_art_image_thumbnail_url": "https://images.rapgenius.com/a0b971addd5197d2d73db3d99c1d56e9.300x300x1.png",
   "song_art_image_url": "https://images.rapgenius.com/a0b971addd5197d2d73db3d99c1d56e9.1000x1000x1.png",
   "stats": {
    "accepted_annotations": 3,
    "contributors": 7,
    "iq_earners": 7,
    "transcribers": 1,
    "unreviewed_annotations": 1,
    "verified_annotations": 0,
    "hot": false,
    "pageviews": 43064
   },
   "title": "Raindrops",
   "title_with_featured": "Raindrops (Ft.\u00a0Kerli)",
   "url": "https://genius.com/Snbrn-raindrops-lyrics",
   "featured_artists": [
    {
     "api_path": "/artists/48767",
     "header_image_url": "https://images.genius.com/d06e3779dc0cff192cd139ab11f5001b.770x770x1.png",
     "id": 48767,
     "image_url": "https://images.genius.com/471ae27d7912ebe4cc686a3e14be9c0b.770x770x1.png",
     "is_meme_verified": false,
     "is_verified": false,
     "name": "Kerli",
     "url": "https://genius.com/artists/Kerli"
    }
   ],
   "primary_artist": {
    "api_path": "/artists/214052",
    "header_image_url": "https://images.genius.com/e7777c94775b993077916a20990ac857.710x710x1.png",
    "id": 214052,
    "image_url": "https://images.genius.com/e7777c94775b993077916a20990ac857.710x710x1.png",
    "is_meme_verified": false,
    "is_verified": false,
    "name": "SNBRN",
    "url": "https://genius.com/artists/Snbrn"
   },
   "apple_music_id": null,
   "apple_music_player_url": "https://genius.com/songs/672294/apple_music_player",
   "description": {
    "plain": "\u201cRaindrops\u201d is a single featuring Estonian pop singer Kerli.\n\nShe sings about feeling finally in love with someone else and wants him to be her lover."
   },
   "embed_content": "<div id='rg_embed_link_672294' class='rg_embed_link' data-song-id='672294'>Read <a href='https://genius.com/Snbrn-raindrops-lyrics'>\u201cRaindrops\u201d by SNBRN</a> on Genius</div> <script crossorigin src='//genius.com/songs/672294/embed.js'></script>",
   "featured_video": false,
   "lyrics_placeholder_reason": null,
   "recording_location": null,
   "release_date": "2015-01-20",
   "current_user_metadata": {
    "permissions": [
     "see_pageviews",
     "view_apple_music_player",
     "view_recommendations",
     "view_song_story_gallery"
    ],
    "excluded_permissions": [
     "follow",
     "award_transcription_iq",
     "remove_transcription_iq",
     "pyong",
     "edit_lyrics",
     "view_annotation_engagement_data",
     "publish",
     "unpublish",
     "edit_spotify_details",
     "hide",
     "unhide",
     "toggle_featured_video",
     "add_pinned_annotation_to",
     "add_community_annotation_to",
     "destroy",
     "mark_as_not_spam",
     "edit_spotify_annotations_for",
     "verify_lyrics",
     "unverify_lyrics",
     "edit_anything",
     "edit_any_media",
     "edit",
     "rename",
     "edit_tags",
     "reindex",
     "view_lyrics_synchronization",
     "enable_media",
     "disable_media",
     "edit_lyrics_or_annotation_brackets",
     "see_editorial_indicators",
     "view_attribution_visualization",
     "edit_annotation_brackets",
     "preview_lyrics_for_export",
     "hide_apple_player",
     "unhide_apple_player",
     "trigger_apple_match",
     "mark_lyrics_evaluation_as_complete",
     "mark_lyrics_evaluation_as_staff_approved",
     "unmark_lyrics_evaluation_as_complete",
     "mark_lyrics_evaluation_as_un_staff_approved",
     "view_transcriber_media_player",
     "override_apple_match",
     "set_song_color_gradient",
     "mark_as_hot",
     "unmark_as_hot",
     "view_relationships_page",
     "edit_youtube_url",
     "edit_soundcloud_url",
     "edit_spotify_uuid",
     "edit_vevo_url",
     "create_comment",
     "moderate_annotations",
     "create_annotation",
     "see_short_id",
     "manage_chart_item",
     "create_tag",
     "propose_lyrics_edit",
     "view_lyrics_edit_proposals_on_song",
     "create_question"
    ],
    "interactions": {
     "pyong": false,
     "following": false
    },
    "relationships": {},
    "iq_by_action": {}
   },
   "album": null,
   "custom_performances": [
    {
     "label": "Label",
     "artists": [
      {
       "api_path": "/artists/1046316",
       "header_image_url": "https://images.genius.com/23b073c0728a919485c9971f5031faed.500x500x1.jpg",
       "id": 1046316,
       "image_url": "https://images.genius.com/af896900f10aa68a1f4e7f02d7df1a49.900x900x1.jpg",
       "is_meme_verified": false,
       "is_verified": false,
       "name": "Ultra Records",
       "url": "https://genius.com/artists/Ultra-records"
      }
     ]
    }
   ],
   "description_annotation": {
    "_type": "referent",
    "annotator_id": 70148,
    "annotator_login": "chihuahua0",
    "api_path": "/referents/4712745",
    "classification": "accepted",
    "fragment": "Raindrops",
    "id": 4712745,
    "is_description": true,
    "path": "/4712745/Snbrn-raindrops/Raindrops",
    "range": {
     "content": "Raindrops"
    },
    "song_id": 672294,
    "url": "https://genius.com/4712745/Snbrn-raindrops/Raindrops",
    "verified_annotator_ids": [],
    "annotatable": {
     "api_path": "/songs/672294",
     "client_timestamps": {
      "updated_by_human_at": 1589204395,
      "lyrics_updated_at": 1589204395
     },
     "context": "SNBRN",
     "id": 672294,
     "image_url": "https://images.rapgenius.com/a0b971addd5197d2d73db3d99c1d56e9.1000x1000x1.png",
     "link_title": "Raindrops by\u00a0SNBRN (Ft.\u00a0Kerli)",
     "title": "Raindrops",
     "type": "Song",
     "url": "https://genius.com/Snbrn-raindrops-lyrics"
    },
    "annotations": [
     {
      "api_path": "/annotations/4712745",
      "body": {
       "plain": "\u201cRaindrops\u201d is a single featuring Estonian pop singer Kerli.\n\nShe sings about feeling finally in love with someone else and wants him to be her lover."
      },
      "comment_count": 1,
      "community": true,
      "custom_preview": null,
      "has_voters": true,
      "id": 4712745,
      "pinned": false,
      "share_url": "https://genius.com/4712745",
      "source": null,
      "state": "accepted",
      "url": "https://genius.com/4712745/Snbrn-raindrops/Raindrops",
      "verified": false,
      "votes_total": 5,
      "current_user_metadata": {
       "permissions": [],
       "excluded_permissions": [
        "vote",
        "edit",
        "cosign",
        "uncosign",
        "destroy",
        "accept",
        "reject",
        "see_unreviewed",
        "clear_votes",
        "propose_edit_to",
        "pin_to_profile",
        "unpin_from_profile",
        "update_source",
        "edit_custom_preview",
        "create_comment"
       ],
       "interactions": {
        "cosign": false,
        "pyong": false,
        "vote": null
       },
       "iq_by_action": {}
      },
      "authors": [
       {
        "attribution": 0.9285714285714286,
        "pinned_role": null,
        "user": {
         "api_path": "/users/70148",
         "avatar": {
          "tiny": {
           "url": "https://images.genius.com/avatars/tiny/794efa2bc6c5b7b400f6362854b28f4d",
           "bounding_box": {
            "width": 16,
            "height": 16
           }
          },
          "thumb": {
           "url": "https://images.genius.com/avatars/thumb/794efa2bc6c5b7b400f6362854b28f4d",
           "bounding_box": {
            "width": 32,
            "height": 32
           }
          },
          "small": {
           "url": "https://images.genius.com/avatars/small/794efa2bc6c5b7b400f6362854b28f4d",
           "bounding_box": {
            "width": 100,
            "height": 100
           }
          },
          "medium": {
           "url": "https://images.genius.com/avatars/medium/794efa2bc6c5b7b400f6362854b28f4d",
           "bounding_box": {
            "width": 300,
            "height": 400
           }
          }
         },
         "header_image_url": "https://images.genius.com/avatars/medium/794efa2bc6c5b7b400f6362854b28f4d",
         "human_readable_role_for_display": "Contributor",
         "id": 70148,
         "iq": 187094,
         "login": "chihuahua0",
         "name": "Chihuahua0",
         "role_for_display": "contributor",
         "url": "https://genius.com/chihuahua0",
         "current_user_metadata": {
          "permissions": [],
          "excluded_permissions": [
           "follow"
          ],
          "interactions": {
           "following": false
          }
         }
        }
       },
       {
        "attribution": 0.07142857142857144,
        "pinned_role": null,
        "user": {
         "api_path": "/users/1459153",
         "avatar": {
          "tiny": {
           "url": "https://images.rapgenius.com/avatars/tiny/6ebd8dc01557cd0ca96200ad8c840930",
           "bounding_box": {
            "width": 16,
            "height": 16
           }
          },
          "thumb": {
           "url": "https://images.rapgenius.com/avatars/thumb/6ebd8dc01557cd0ca96200ad8c840930",
           "bounding_box": {
            "width": 32,
            "height": 32
           }
          },
          "small": {
           "url": "https://images.rapgenius.com/avatars/small/6ebd8dc01557cd0ca96200ad8c840930",
           "bounding_box": {
            "width": 100,
            "height": 100
           }
          },
          "medium": {
           "url": "https://images.rapgenius.com/avatars/medium/6ebd8dc01557cd0ca96200ad8c840930",
           "bounding_box": {
            "width": 300,
            "height": 400
           }
          }
         },
         "header_image_url": "https://images.rapgenius.com/avatars/medium/6ebd8dc01557cd0ca96200ad8c840930",
         "human_readable_role_for_display": null,
         "id": 1459153,
         "iq": 111,
         "login": "cathalin",
         "name": "cathalin",
         "role_for_display": null,
         "url": "https://genius.com/cathalin",
         "current_user_metadata": {
          "permissions": [],
          "excluded_permissions": [
           "follow"
          ],
          "interactions": {
           "following": false
          }
         }
        }
       }
      ],
      "cosigned_by": [],
      "rejection_comment": null,
      "verified_by": null
     }
    ]
   },
   "lyrics_marked_complete_by": null,
   "lyrics_marked_staff_approved_by": null,
   "media": [
    {
     "native_uri": "spotify:track:6PjitpdnGluMNLv0VeCVe5",
     "provider": "spotify",
     "type": "audio",
     "url": "https://open.spotify.com/track/6PjitpdnGluMNLv0VeCVe5"
    },
    {
     "attribution": "kerli",
     "provider": "soundcloud",
     "type": "audio",
     "url": "https://soundcloud.com/kerli/raindrops-ft-kerli"
    },
    {
     "provider": "youtube",
     "start": 0,
     "type": "video",
     "url": "http://www.youtube.com/watch?v=KmV4S0cckCI"
    }
   ],
   "producer_artists": [
    {
     "api_path": "/artists/214052",
     "header_image_url": "https://images.genius.com/e7777c94775b993077916a20990ac857.710x710x1.png",
     "id": 214052,
     "image_url": "https://images.genius.com/e7777c94775b993077916a20990ac857.710x710x1.png",
     "is_meme_verified": false,
     "is_verified": false,
     "name": "SNBRN",
     "url": "https://genius.com/artists/Snbrn"
    }
   ],
   "song_relationships": [
    {
     "relationship_type": "samples",
     "type": "samples",
     "songs": []
    },
    {
     "relationship_type": "sampled_in",
     "type": "sampled_in",
     "songs": []
    },
    {
     "relationship_type": "interpolates",
     "type": "interpolates",
     "songs": []
    },
    {
     "relationship_type": "interpolated_by",
     "type": "interpolated_by",
     "songs": []
    },
    {
     "relationship_type": "cover_of",
     "type": "cover_of",
     "songs": []
    },
    {
     "relationship_type": "covered_by",
     "type": "covered_by",
     "songs": []
    },
    {
     "relationship_type": "remix_of",
     "type": "remix_of",
     "songs": []
    },
    {
     "relationship_type": "remixed_by",
     "type": "remixed_by",
     "songs": []
    },
    {
     "relationship_type": "live_version_of",
     "type": "live_version_of",
     "songs": []
    },
    {
     "relationship_type": "performed_live_as",
     "type": "performed_live_as",
     "songs": []
    },
    {
     "relationship_type": "translation_of",
     "type": "translation_of",
     "songs": []
    },
    {
     "relationship_type": "translations",
     "type": "translations",
     "songs": []
    }
   ],
   "translation_songs": [],
   "verified_annotations_by": [],
   "verified_contributors": [],
   "verified_lyrics_by": [],
   "writer_artists": [
    {
     "api_path": "/artists/214052",
     "header_image_url": "https://images.genius.com/e7777c94775b993077916a20990ac857.710x710x1.png",
     "id": 214052,
     "image_url": "https://images.genius.com/e7777c94775b993077916a20990ac857.710x710x1.png",
     "is_meme_verified": false,
     "is_verified": false,
     "name": "SNBRN",
     "url": "https://genius.com/artists/Snbrn"
    },
    {
     "api_path": "/artists/48767",
     "header_image_url": "https://images.genius.com/d06e3779dc0cff192cd139ab11f5001b.770x770x1.png",
     "id": 48767,
     "image_url": "https://images.genius.com/471ae27d7912ebe4cc686a3e14be9c0b.770x770x1.png",
     "is_meme_verified": false,
     "is_verified": false,
     "name": "Kerli",
     "url": "https://genius.com/artists/Kerli"
    }
   ],
   "artist": "SNBRN",
   "lyrics": "7 ContributorsRaindrops Lyrics[Verse 1]\nLike raindrops from the desert sky\nFor you I've been waiting\nLike seeing stars and endless nights\nFor you I'll be waiting\n\n[Pre-Chorus]\nIt's like I can breathe\nFinally\nCan we stay like this forever?\n\n[Chorus]\nWon't you take me over?\nCome a little bit closer\nA little bit closer\nAnd wake up together\nBring me up from the under\nA little bit closer\nA little bit closer\nCan we stay like this forever?\nWon't you take me over?\nCome a little bit closer\nA little bit closer\nAnd wake up together\nBring me up from the under\nA little bit closer\nA little bit closer\nCan we stay like this forever?\nWon't you take me over?\nCome a little bit closer\nA little bit closer\nAnd wake up together\nBring me up from the under\nA little bit closer\nA little bit closer\nCan we stay like this forever?\nYou might also like[Verse 2]\nLike raindrops from the desert sky\nFor you I've be waiting\nWith your touch I come alive\nFor you I'll be waiting\n\n[Pre-Chorus]\nIt's like I can breathe\nFinally\nCan we stay like this forever?\n\n[Chorus]\nWon't you take me over?\nCome a little bit closer\nA little bit closer\nAnd wake up together\nBring me up from the under\nA little bit closer\nA little bit closer\nCan we stay like this forever?\nWon't you take me over?\nCome a little bit closer\nA little bit closer\nAnd wake up together\nBring me up from the under\nA little bit closer\nA little bit closer\nCan we stay like this forever?\nWon't you take me over?\nCome a little bit closer\nA little bit closer\nAnd wake up together\nBring me up from the under\nA little bit closer\nA little bit closer\nCan we stay like this forever?\n[Verse 2]\nLike raindrops from the desert sky\nFor you I've be waiting\nWith your touch I come alive\nFor you I'll be waiting17Embed"
  },
  {
   "annotation_count": 1,
   "api_path": "/songs/2411896",
   "artist_names": "SNBRN (Ft. Nate Dogg)",
   "full_title": "Gangsta Walk by\u00a0SNBRN (Ft.\u00a0Nate\u00a0Dogg)",
   "header_image_thumbnail_url": "https://images.rapgenius.com/a56d6ca7806686c27a72ac4a26a77e19.300x300x1.jpg",
   "header_image_url": "https://images.rapgenius.com/a56d6ca7806686c27a72ac4a26a77e19.1000x1000x1.jpg",
   "id": 2411896,
   "language": "en",
   "lyrics_owner_id": 672397,
   "lyrics_state": "complete",
   "path": "/Snbrn-gangsta-walk-lyrics",
   "pyongs_count": null,
   "relationships_index_url": "https://genius.com/Snbrn-gangsta-walk-sample",
   "release_date_components": null,
   "release_date_for_display": null,
   "release_date_with_abbreviated_month_for_display": null,
   "song_art_image_thumbnail_url": "https://images.rapgenius.com/a56d6ca7806686c27a72ac4a26a77e19.300x300x1.jpg",
   "song_art_image_url": "https://images.rapgenius.com/a56d6ca7806686c27a72ac4a26a77e19.1000x1000x1.jpg",
   "stats": {
    "accepted_annotations": 0,
    "contributors": 3,
    "iq_earners": 3,
    "transcribers": 1,
    "unreviewed_annotations": 1,
    "verified_annotations": 0,
    "hot": false,
    "pageviews": 27079
   },
   "title": "Gangsta Walk",
   "title_with_featured": "Gangsta Walk (Ft.\u00a0Nate\u00a0Dogg)",
   "url": "https://genius.com/Snbrn-gangsta-walk-lyrics",
   "featured_artists": [
    {
     "api_path": "/artists/149",
     "header_image_url": "https://images.genius.com/2bb785d49812a68762e5ffdf3b167e3e.437x437x1.jpg",
     "id": 149,
     "image_url": "https://images.genius.com/2bb785d49812a68762e5ffdf3b167e3e.437x437x1.jpg",
     "is_meme_verified": false,
     "is_verified": false,
     "name": "Nate Dogg",
     "url": "https://genius.com/artists/Nate-dogg"
    }
   ],
   "primary_artist": {
    "api_path": "/artists/214052",
    "header_image_url": "https://images.genius.com/e7777c94775b993077916a20990ac857.710x710x1.png",
    "id": 214052,
    "image_url": "https://images.genius.com/e7777c94775b993077916a20990ac857.710x710x1.png",
    "is_meme_verified": false,
    "is_verified": false,
    "name": "SNBRN",
    "url": "https://genius.com/artists/Snbrn"
   },
   "apple_music_id": "1072495647",
   "apple_music_player_url": "https://genius.com/songs/2411896/apple_music_player",
   "description": {
    "plain": "?"
   },
   "embed_content": "<div id='rg_embed_link_2411896' class='rg_embed_link' data-song-id='2411896'>Read <a href='https://genius.com/Snbrn-gangsta-walk-lyrics'>\u201cGangsta Walk\u201d by SNBRN</a> on Genius</div> <script crossorigin src='//genius.com/songs/2411896/embed.js'></script>",
   "featured_video": false,
   "lyrics_placeholder_reason": null,
   "recording_location": null,
   "release_date": null,
   "current_user_metadata": {
    "permissions": [
     "see_pageviews",
     "view_apple_music_player",
     "view_recommendations",
     "view_relationships_page",
     "view_song_story_gallery"
    ],
    "excluded_permissions": [
     "follow",
     "award_transcription_iq",
     "remove_transcription_iq",
     "pyong",
     "edit_lyrics",
     "view_annotation_engagement_data",
     "publish",
     "unpublish",
     "edit_spotify_details",
     "hide",
     "unhide",
     "toggle_featured_video",
     "add_pinned_annotation_to",
     "add_community_annotation_to",
     "destroy",
     "mark_as_not_spam",
     "edit_spotify_annotations_for",
     "verify_lyrics",
     "unverify_lyrics",
     "edit_anything",
     "edit_any_media",
     "edit",
     "rename",
     "edit_tags",
     "reindex",
     "view_lyrics_synchronization",
     "enable_media",
     "disable_media",
     "edit_lyrics_or_annotation_brackets",
     "see_editorial_indicators",
     "view_attribution_visualization",
     "edit_annotation_brackets",
     "preview_lyrics_for_export",
     "hide_apple_player",
     "unhide_apple_player",
     "trigger_apple_match",
     "mark_lyrics_evaluation_as_complete",
     "mark_lyrics_evaluation_as_staff_approved",
     "unmark_lyrics_evaluation_as_complete",
     "mark_lyrics_evaluation_as_un_staff_approved",
     "view_transcriber_media_player",
     "override_apple_match",
     "set_song_color_gradient",
     "mark_as_hot",
     "unmark_as_hot",
     "edit_youtube_url",
     "edit_soundcloud_url",
     "edit_spotify_uuid",
     "edit_vevo_url",
     "create_comment",
     "moderate_annotations",
     "create_annotation",
     "see_short_id",
     "manage_chart_item",
     "create_tag",
     "propose_lyrics_edit",
     "view_lyrics_edit_proposals_on_song",
     "create_question"
    ],
    "interactions": {
     "pyong": false,
     "following": false
    },
    "relationships": {},
    "iq_by_action": {}
   },
   "album": null,
   "custom_performances": [],
   "description_annotation": {
    "_type": "referent",
    "annotator_id": 672397,
    "annotator_login": "Freeus",
    "api_path": "/referents/8564508",
    "classification": "needs_exegesis",
    "fragment": "Gangsta Walk",
    "id": 8564508,
    "is_description": true,
    "path": "/8564508/Snbrn-gangsta-walk/Gangsta-walk",
    "range": {
     "content": "Gangsta Walk"
    },
    "song_id": 2411896,
    "url": "https://genius.com/8564508/Snbrn-gangsta-walk/Gangsta-walk",
    "verified_annotator_ids": [],
    "annotatable": {
     "api_path": "/songs/2411896",
     "client_timestamps": {
      "updated_by_human_at": 1464900945,
      "lyrics_updated_at": 1464900945
     },
     "context": "SNBRN",
     "id": 2411896,
     "image_url": "https://images.rapgenius.com/a56d6ca7806686c27a72ac4a26a77e19.1000x1000x1.jpg",
     "link_title": "Gangsta Walk by\u00a0SNBRN (Ft.\u00a0Nate\u00a0Dogg)",
     "title": "Gangsta Walk",
     "type": "Song",
     "url": "https://genius.com/Snbrn-gangsta-walk-lyrics"
    },
    "annotations": [
     {
      "api_path": "/annotations/8564508",
      "body": {
       "plain": ""
      },
      "comment_count": 0,
      "community": true,
      "custom_preview": null,
      "has_voters": false,
      "id": 8564508,
      "pinned": false,
      "share_url": "https://genius.com/8564508",
      "source": null,
      "state": "needs_exegesis",
      "url": "https://genius.com/8564508/Snbrn-gangsta-walk/Gangsta-walk",
      "verified": false,
      "votes_total": 0,
      "current_user_metadata": {
       "permissions": [],
       "excluded_permissions": [
        "vote",
        "edit",
        "cosign",
        "uncosign",
        "destroy",
        "accept",
        "reject",
        "see_unreviewed",
        "clear_votes",
        "propose_edit_to",
        "pin_to_profile",
        "unpin_from_profile",
        "update_source",
        "edit_custom_preview",
        "create_comment"
       ],
       "interactions": {
        "cosign": false,
        "pyong": false,
        "vote": null
       },
       "iq_by_action": {}
      },
      "authors": [
       {
        "attribution": 1.0,
        "pinned_role": null,
        "user": {
         "api_path": "/users/672397",
         "avatar": {
          "tiny": {
           "url": "https://images.genius.com/avatars/tiny/78e75f2eaf392b087b9636bf18926805",
           "bounding_box": {
            "width": 16,
            "height": 16
           }
          },
          "thumb": {
           "url": "https://images.genius.com/avatars/thumb/78e75f2eaf392b087b9636bf18926805",
           "bounding_box": {
            "width": 32,
            "height": 32
           }
          },
          "small": {
           "url": "https://images.genius.com/avatars/small/78e75f2eaf392b087b9636bf18926805",
           "bounding_box": {
            "width": 100,
            "height": 100
           }
          },
          "medium": {
           "url": "https://images.genius.com/avatars/medium/78e75f2eaf392b087b9636bf18926805",
           "bounding_box": {
            "width": 300,
            "height": 400
           }
          }
         },
         "header_image_url": "https://images.genius.com/avatars/medium/78e75f2eaf392b087b9636bf18926805",
         "human_readable_role_for_display": "Editor",
         "id": 672397,
         "iq": 499748,
         "login": "Freeus",
         "name": "\u15f4velyn",
         "role_for_display": "editor",
         "url": "https://genius.com/Freeus",
         "current_user_metadata": {
          "permissions": [],
          "excluded_permissions": [
           "follow"
          ],
          "interactions": {
           "following": false
          }
         }
        }
       }
      ],
      "cosigned_by": [],
      "rejection_comment": null,
      "verified_by": null
     }
    ]
   },
   "lyrics_marked_complete_by": null,
   "lyrics_marked_staff_approved_by": null,
   "media": [
    {
     "native_uri": "spotify:track:6AAw43DJbIysnD0DwVurGd",
     "provider": "spotify",
     "type": "audio",
     "url": "https://open.spotify.com/track/6AAw43DJbIysnD0DwVurGd"
    },
    {
     "provider": "youtube",
     "start": 0,
     "type": "video",
     "url": "http://www.youtube.com/watch?v=r0gmAq_TkAA"
    }
   ],
   "producer_artists": [],
   "song_relationships": [
    {
     "relationship_type": "samples",
     "type": "samples",
     "url": null,
     "songs": []
    },
    {
     "relationship_type": "sampled_in",
     "type": "sampled_in",
     "url": null,
     "songs": [
      {
       "annotation_count": 0,
       "api_path": "/songs/4784398",
       "artist_names": "CVPELLV",
       "full_title": "Gangsta Walk by\u00a0CVPELLV",
       "header_image_thumbnail_url": "https://images.genius.com/dcf5187836bbf5270349a9fa70b4c0d5.300x300x1.jpg",
       "header_image_url": "https://images.genius.com/dcf5187836bbf5270349a9fa70b4c0d5.1000x1000x1.jpg",
       "id": 4784398,
       "language": "en",
       "lyrics_owner_id": 7563636,
       "lyrics_state": "complete",
       "path": "/Cvpellv-gangsta-walk-lyrics",
       "pyongs_count": null,
       "relationships_index_url": "https://genius.com/Cvpellv-gangsta-walk-sample",
       "release_date_components": null,
       "release_date_for_display": null,
       "release_date_with_abbreviated_month_for_display": null,
       "song_art_image_thumbnail_url": "https://images.genius.com/dcf5187836bbf5270349a9fa70b4c0d5.300x300x1.jpg",
       "song_art_image_url": "https://images.genius.com/dcf5187836bbf5270349a9fa70b4c0d5.1000x1000x1.jpg",
       "stats": {
        "unreviewed_annotations": 0,
        "hot": false
       },
       "title": "Gangsta Walk",
       "title_with_featured": "Gangsta Walk",
       "url": "https://genius.com/Cvpellv-gangsta-walk-lyrics",
       "featured_artists": [],
       "primary_artist": {
        "api_path": "/artists/161765",
        "header_image_url": "https://images.genius.com/a817ad8c39f6a65417653430cd11a267.795x200x1.jpg",
        "id": 161765,
        "image_url": "https://images.genius.com/a7968a176bbca6e2206f1d69b866af95.852x852x1.jpg",
        "is_meme_verified": false,
        "is_verified": false,
        "name": "CVPELLV",
        "url": "https://genius.com/artists/Cvpellv"
       }
      }
     ]
    },
    {
     "relationship_type": "interpolates",
     "type": "interpolates",
     "url": null,
     "songs": []
    },
    {
     "relationship_type": "interpolated_by",
     "type": "interpolated_by",
     "url": null,
     "songs": []
    },
    {
     "relationship_type": "cover_of",
     "type": "cover_of",
     "url": null,
     "songs": []
    },
    {
     "relationship_type": "covered_by",
     "type": "covered_by",
     "url": null,
     "songs": []
    },
    {
     "relationship_type": "remix_of",
     "type": "remix_of",
     "url": null,
     "songs": []
    },
    {
     "relationship_type": "remixed_by",
     "type": "remixed_by",
     "url": null,
     "songs": []
    },
    {
     "relationship_type": "live_version_of",
     "type": "live_version_of",
     "url": null,
     "songs": []
    },
    {
     "relationship_type": "performed_live_as",
     "type": "performed_live_as",
     "url": null,
     "songs": []
    },
    {
     "relationship_type": "translation_of",
     "type": "translation_of",
     "url": null,
     "songs": []
    },
    {
     "relationship_type": "translations",
     "type": "translations",
     "url": null,
     "songs": []
    }
   ],
   "translation_songs": [],
   "verified_annotations_by": [],
   "verified_contributors": [],
   "verified_lyrics_by": [],
   "writer_artists": [],
   "artist": "SNBRN",
   "lyrics": "3 ContributorsGangsta Walk Lyrics[Verse 1: Nate Dogg]\nHey little mama with that tight dress on\nI got a small proposition for you (ah, ah, ah, ah)\nYou look kinda sexy got it going on\nHere's what I want you to do\n(Here's what I want you to do)\nCome a little closer, let me see that thong\nLet me slide this number to you (Ah, ah, ah)\nYou can catch me in them streets with my blue khakis on\nIn my Chuck Taylors smoking blunts with my crew\n(Gangsta walk)\n\n[Hook: Nate Dogg]\nHey, hey, hey, hey\nAll my niggas do the gangsta walk\nAll my niggas do the gangsta walk\nHey, hey, hey, hey\nAll my bitches do the gangsta walk\nLet me see you do the gangsta walk\nNo matter what they say\nAll my niggas do the gangsta walk\nAll my niggas do the gangsta walk\nBlow trees anyway\nAll my bitches do the gangsta walk\nLet me see you do the gangsta walk\nHey, hey\nYou might also like[Pre-Hook]\nHomie give it up if you ballin'\nHomie give it up for yourself\nLadies pick it up let's keep calling\nBaby showing off out the west\n\n[Hook]\nAll my niggas do the gangsta walk\nAll my niggas do the gangsta walk\nHey, hey, hey, hey\nAll my bitches do the gangsta walk\nLet me see you do the gangsta walk\nNo matter what they say\nAll my niggas do the gangsta walk\nAll my niggas do the gangsta walk\nBlow trees anyway\nAll my bitches do the gangsta walk\nLet me see you do the gangsta walk\nHey, hey\n\n[Verse 2: Nate Dogg]\nIt's 6 in the morning, we still going strong\nAnd we ran out of weed at about two (oh no)\nMust be the music, got these gangstas gone\n(Must be the music)\nI'm tryna play this funk down on you\n[Pre-Hook]\nHomie give it up if you ballin'\nHomie give it up for yourself\nLadies pick it up let's keep calling\nBaby showing off out the west\n\n[Hook]\nAll my niggas do the gangsta walk\nAll my niggas do the gangsta walk\nHey, hey, hey, hey\nAll my bitches do the gangsta walk\nLet me see you do the gangsta walk\nNo matter what they say\nAll my niggas do the gangsta walk\nAll my niggas do the gangsta walk\nBlow trees anyway\nAll my bitches do the gangsta walk\nLet me see you do the gangsta walk\nHey, hey, hey, hey\nAll my niggas do the gangsta walk\nAll my niggas do the gangsta walk\nAll my bitches do the gangsta walk\nLet me see you do the gangsta walk\nNo matter what they say\nAll my niggas do the gangsta walk\nAll my niggas do the gangsta walk\nBlow trees anyway\nAll my bitches do the gangsta walk\nLet me see you do the gangsta walk\nHey, heyEmbed"
  },
  {
   "annotation_count": 1,
   "api_path": "/songs/2480629",
   "artist_names": "SNBRN (Ft. Holly Winter)",
   "full_title": "Sometimes by\u00a0SNBRN (Ft.\u00a0Holly\u00a0Winter)",
   "header_image_thumbnail_url": "https://images.genius.com/401ffbeebc3be0ae420e54ab442a6991.300x300x1.jpg",
   "header_image_url": "https://images.genius.com/401ffbeebc3be0ae420e54ab442a6991.1000x1000x1.jpg",
   "id": 2480629,
   "language": "en",
   "lyrics_owner_id": 93685,
   "lyrics_state": "complete",
   "path": "/Snbrn-sometimes-lyrics",
   "pyongs_count": null,
   "relationships_index_url": "https://genius.com/Snbrn-sometimes-sample",
   "release_date_components": {
    "year": 2016,
    "month": 5,
    "day": 27
   },
   "release_date_for_display": "May 27, 2016",
   "release_date_with_abbreviated_month_for_display": "May. 27, 2016",
   "song_art_image_thumbnail_url": "https://images.genius.com/401ffbeebc3be0ae420e54ab442a6991.300x300x1.jpg",
   "song_art_image_url": "https://images.genius.com/401ffbeebc3be0ae420e54ab442a6991.1000x1000x1.jpg",
   "stats": {
    "accepted_annotations": 0,
    "contributors": 2,
    "iq_earners": 2,
    "transcribers": 1,
    "unreviewed_annotations": 1,
    "verified_annotations": 0,
    "hot": false
   },
   "title": "Sometimes",
   "title_with_featured": "Sometimes (Ft.\u00a0Holly\u00a0Winter)",
   "url": "https://genius.com/Snbrn-sometimes-lyrics",
   "featured_artists": [
    {
     "api_path": "/artists/674208",
     "header_image_url": "https://assets.genius.com/images/default_avatar_300.png?1682450960",
     "id": 674208,
     "image_url": "https://assets.genius.com/images/default_avatar_300.png?1682450960",
     "is_meme_verified": false,
     "is_verified": false,
     "name": "Holly Winter",
     "url": "https://genius.com/artists/Holly-winter"
    }
   ],
   "primary_artist": {
    "api_path": "/artists/214052",
    "header_image_url": "https://images.genius.com/e7777c94775b993077916a20990ac857.710x710x1.png",
    "id": 214052,
    "image_url": "https://images.genius.com/e7777c94775b993077916a20990ac857.710x710x1.png",
    "is_meme_verified": false,
    "is_verified": false,
    "name": "SNBRN",
    "url": "https://genius.com/artists/Snbrn"
   },
   "apple_music_id": "1110215339",
   "apple_music_player_url": "https://genius.com/songs/2480629/apple_music_player",
   "description": {
    "plain": "?"
   },
   "embed_content": "<div id='rg_embed_link_2480629' class='rg_embed_link' data-song-id='2480629'>Read <a href='https://genius.com/Snbrn-sometimes-lyrics'>\u201cSometimes\u201d by SNBRN</a> on Genius</div> <script crossorigin src='//genius.com/songs/2480629/embed.js'></script>",
   "featured_video": false,
   "lyrics_placeholder_reason": null,
   "recording_location": null,
   "release_date": "2016-05-27",
   "current_user_metadata": {
    "permissions": [
     "view_apple_music_player",
     "view_recommendations",
     "view_song_story_gallery"
    ],
    "excluded_permissions": [
     "follow",
     "award_transcription_iq",
     "remove_transcription_iq",
     "see_pageviews",
     "pyong",
     "edit_lyrics",
     "view_annotation_engagement_data",
     "publish",
     "unpublish",
     "edit_spotify_details",
     "hide",
     "unhide",
     "toggle_featured_video",
     "add_pinned_annotation_to",
     "add_community_annotation_to",
     "destroy",
     "mark_as_not_spam",
     "edit_spotify_annotations_for",
     "verify_lyrics",
     "unverify_lyrics",
     "edit_anything",
     "edit_any_media",
     "edit",
     "rename",
     "edit_tags",
     "reindex",
     "view_lyrics_synchronization",
     "enable_media",
     "disable_media",
     "edit_lyrics_or_annotation_brackets",
     "see_editorial_indicators",
     "view_attribution_visualization",
     "edit_annotation_brackets",
     "preview_lyrics_for_export",
     "hide_apple_player",
     "unhide_apple_player",
     "trigger_apple_match",
     "mark_lyrics_evaluation_as_complete",
     "mark_lyrics_evaluation_as_staff_approved",
     "unmark_lyrics_evaluation_as_complete",
     "mark_lyrics_evaluation_as_un_staff_approved",
     "view_transcriber_media_player",
     "override_apple_match",
     "set_song_color_gradient",
     "mark_as_hot",
     "unmark_as_hot",
     "view_relationships_page",
     "edit_youtube_url",
     "edit_soundcloud_url",
     "edit_spotify_uuid",
     "edit_vevo_url",
     "create_comment",
     "moderate_annotations",
     "create_annotation",
     "see_short_id",
     "manage_chart_item",
     "create_tag",
     "propose_lyrics_edit",
     "view_lyrics_edit_proposals_on_song",
     "create_question"
    ],
    "interactions": {
     "pyong": false,
     "following": false
    },
    "relationships": {},
    "iq_by_action": {}
   },
   "album": null,
   "custom_performances": [],
   "description_annotation": {
    "_type": "referent",
    "annotator_id": 93685,
    "annotator_login": "killersnowtiger",
    "api_path": "/referents/9221829",
    "classification": "needs_exegesis",
    "fragment": "Sometimes",
    "id": 9221829,
    "is_description": true,
    "path": "/9221829/Snbrn-sometimes/Sometimes",
    "range": {
     "content": "Sometimes"
    },
    "song_id": 2480629,
    "url": "https://genius.com/9221829/Snbrn-sometimes/Sometimes",
    "verified_annotator_ids": [],
    "annotatable": {
     "api_path": "/songs/2480629",
     "client_timestamps": {
      "updated_by_human_at": 1552068286,
      "lyrics_updated_at": 1552068286
     },
     "context": "SNBRN",
     "id": 2480629,
     "image_url": "https://images.genius.com/401ffbeebc3be0ae420e54ab442a6991.1000x1000x1.jpg",
     "link_title": "Sometimes by\u00a0SNBRN (Ft.\u00a0Holly\u00a0Winter)",
     "title": "Sometimes",
     "type": "Song",
     "url": "https://genius.com/Snbrn-sometimes-lyrics"
    },
    "annotations": [
     {
      "api_path": "/annotations/9221829",
      "body": {
       "plain": ""
      },
      "comment_count": 0,
      "community": true,
      "custom_preview": null,
      "has_voters": false,
      "id": 9221829,
      "pinned": false,
      "share_url": "https://genius.com/9221829",
      "source": null,
      "state": "needs_exegesis",
      "url": "https://genius.com/9221829/Snbrn-sometimes/Sometimes",
      "verified": false,
      "votes_total": 0,
      "current_user_metadata": {
       "permissions": [],
       "excluded_permissions": [
        "vote",
        "edit",
        "cosign",
        "uncosign",
        "destroy",
        "accept",
        "reject",
        "see_unreviewed",
        "clear_votes",
        "propose_edit_to",
        "pin_to_profile",
        "unpin_from_profile",
        "update_source",
        "edit_custom_preview",
        "create_comment"
       ],
       "interactions": {
        "cosign": false,
        "pyong": false,
        "vote": null
       },
       "iq_by_action": {}
      },
      "authors": [
       {
        "attribution": 1.0,
        "pinned_role": null,
        "user": {
         "api_path": "/users/93685",
         "avatar": {
          "tiny": {
           "url": "https://images.genius.com/avatars/tiny/eef1301d558fe7caf2ab0668b8a747e0",
           "bounding_box": {
            "width": 16,
            "height": 16
           }
          },
          "thumb": {
           "url": "https://images.genius.com/avatars/thumb/eef1301d558fe7caf2ab0668b8a747e0",
           "bounding_box": {
            "width": 32,
            "height": 32
           }
          },
          "small": {
           "url": "https://images.genius.com/avatars/small/eef1301d558fe7caf2ab0668b8a747e0",
           "bounding_box": {
            "width": 100,
            "height": 100
           }
          },
          "medium": {
           "url": "https://images.genius.com/avatars/medium/eef1301d558fe7caf2ab0668b8a747e0",
           "bounding_box": {
            "width": 300,
            "height": 400
           }
          }
         },
         "header_image_url": "https://images.genius.com/5d9fd826e38ad61f98aa9b6985263347.1000x263x121.gif",
         "human_readable_role_for_display": "Staff",
         "id": 93685,
         "iq": 1232027,
         "login": "killersnowtiger",
         "name": "\u200bKST",
         "role_for_display": "staff",
         "url": "https://genius.com/killersnowtiger",
         "current_user_metadata": {
          "permissions": [],
          "excluded_permissions": [
           "follow"
          ],
          "interactions": {
           "following": false
          }
         }
        }
       }
      ],
      "cosigned_by": [],
      "rejection_comment": null,
      "verified_by": null
     }
    ]
   },
   "lyrics_marked_complete_by": null,
   "lyrics_marked_staff_approved_by": null,
   "media": [],
   "producer_artists": [],
   "song_relationships": [
    {
     "relationship_type": "samples",
     "type": "samples",
     "songs": []
    },
    {
     "relationship_type": "sampled_in",
     "type": "sampled_in",
     "songs": []
    },
    {
     "relationship_type": "interpolates",
     "type": "interpolates",
     "songs": []
    },
    {
     "relationship_type": "interpolated_by",
     "type": "interpolated_by",
     "songs": []
    },
    {
     "relationship_type": "cover_of",
     "type": "cover_of",
     "songs": []
    },
    {
     "relationship_type": "covered_by",
     "type": "covered_by",
     "songs": []
    },
    {
     "relationship_type": "remix_of",
     "type": "remix_of",
     "songs": []
    },
    {
     "relationship_type": "remixed_by",
     "type": "remixed_by",
     "songs": []
    },
    {
     "relationship_type": "live_version_of",
     "type": "live_version_of",
     "songs": []
    },
    {
     "relationship_type": "performed_live_as",
     "type": "performed_live_as",
     "songs": []
    },
    {
     "relationship_type": "translation_of",
     "type": "translation_of",
     "songs": []
    },
    {
     "relationship_type": "translations",
     "type": "translations",
     "songs": []
    }
   ],
   "translation_songs": [],
   "verified_annotations_by": [],
   "verified_contributors": [],
   "verified_lyrics_by": [],
   "writer_artists": [],
   "artist": "SNBRN",
   "lyrics": "2 ContributorsSometimes Lyrics[Intro]\nSometimes\n\n[Verse 1]\nSometimes the fever in my bones won't break\nI wanna make the same mistakes\nSometimes the brick beneath my feet is real\nThe hotel seats are all I feel\nSometimes the lights can't keep the dark away\nSometimes I beg my enemies to stay\nI love the demons I should hate\nI'm bleeding, but I'm not in pain\nTell me, someone, tell me what is real, what is fake\n\n[Chorus]\nIf it's all in my head, wake me up when I'm dead\nYou can say what you feel, what is fake, what is real\nIf it's all in my mind, let me be, I'll be fine\nWake me up, wake me up, when I'm dead\nIt's all in my head\n\n[Post-Chorus]\nSometimes\nOh, sometimes\nWhen I'm dead, it's all in my head\nSometimes\nOh, sometimes\nYou might also like[Verse 2]\nSometimes I'm better off all alone\nSometimes I'm tossed out like a stone\nSometimes wash my hair and change my clothes\nCatch a train to Barcelon', all the same, nobody knows\nSometimes, oh sometimes\n\n[Chorus]\nIf it's all in my head, wake me up when I'm dead\nYou can say what you feel, what is fake, what is real\nIf it's all in my mind, let me be, I'll be fine\nWake me up, wake me up, when I'm dead\nIt's all in my head\n\n[Post-Chorus]\nIt's all in my head\nIt's all in my head\n\n[Chorus]\nIf it's all in my head, wake me up when I'm dead\nYou can say what you feel, what is fake, what is real\nYou can say, you can say\nWake me up, wake me up, when I'm dead\nIt's all in my head\n\n[Outro]\nSometimes\nWake me up, wake me up, when I'm dead\nIt's all in my headEmbed"
  }
 ]
}