{
 "alternate_names": [
  "Nya Kilgore",
  "YBN NyA",
  "Daddy kaine"
 ],
 "api_path": "/artists/2287247",
 "description": {
  "plain": "Nya Kilgore, known professionally as NextYoungin, or Daddy Kaine, is an American rapper who first appeared on \u201c3 Musketeers\u201d by artist ppcocaine. Pronouns are she/her/daddy. Her bio is usually \u201cHa, ion even rap \ud83d\udc7d\u201d ."
 },
 "facebook_name": null,
 "followers_count": 18,
 "header_image_url": "https://images.genius.com/7f57042cb7726dd74f9550e3823dd999.670x1000x1.jpg",
 "id": 2287247,
 "image_url": "https://images.genius.com/d383eeb0f6f77a9b9a2ea3236dbbadae.285x285x1.jpg",
 "instagram_name": "nextyoungin",
 "is_meme_verified": false,
 "is_verified": false,
 "name": "NextYoungin",
 "translation_artist": false,
 "twitter_name": null,
 "url": "https://genius.com/artists/Nextyoungin",
 "current_user_metadata": {
  "permissions": [
   "view_activity_stream"
  ],
  "excluded_permissions": [
   "edit",
   "edit_images",
   "edit_names",
   "edit_anything",
   "merge",
   "sort_artist_songs",
   "follow",
   "view_contribution_opportunities",
   "edit_translation_artist",
   "see_short_id"
  ],
  "interactions": {
   "following": false
  }
 },
 "description_annotation": {
  "_type": "referent",
  "annotator_id": 9315835,
  "annotator_login": "Crystallisee",
  "api_path": "/referents/20130231",
  "classification": "unreviewed",
  "fragment": "NextYoungin",
  "id": 20130231,
  "is_description": true,
  "path": "/20130231/Nextyoungin/Nextyoungin",
  "range": {
   "content": "NextYoungin"
  },
  "song_id": null,
  "url": "https://genius.com/20130231/Nextyoungin/Nextyoungin",
  "verified_annotator_ids": [],
  "annotatable": {
   "api_path": "/artists/2287247",
   "context": null,
   "id": 2287247,
   "image_url": "https://images.genius.com/d383eeb0f6f77a9b9a2ea3236dbbadae.285x285x1.jpg",
   "link_title": "NextYoungin",
   "title": "NextYoungin",
   "type": "Artist",
   "url": "https://genius.com/artists/Nextyoungin"
  },
  "annotations": [
   {
    "api_path": "/annotations/20130231",
    "body": {
     "plain": "Nya Kilgore, known professionally as NextYoungin, or Daddy Kaine, is an American rapper who first appeared on \u201c3 Musketeers\u201d by artist ppcocaine. Pronouns are she/her/daddy. Her bio is usually \u201cHa, ion even rap \ud83d\udc7d\u201d ."
    },
    "comment_count": 1,
    "community": true,
    "custom_preview": null,
    "has_voters": true,
    "id": 20130231,
    "pinned": false,
    "share_url": "https://genius.com/20130231",
    "source": null,
    "state": "pending",
    "url": "https://genius.com/20130231/Nextyoungin/Nextyoungin",
    "verified": false,
    "votes_total": 2,
    "current_user_metadata": {
     "permissions": [],
     "excluded_permissions": [
      "vote",
      "edit",
      "cosign",
      "uncosign",
      "destroy",
      "accept",
      "reject",
      "see_unreviewed",
      "clear_votes",
      "propose_edit_to",
      "pin_to_profile",
      "unpin_from_profile",
      "update_source",
      "edit_custom_preview",
      "create_comment"
     ],
     "interactions": {
      "cosign": false,
      "pyong": false,
      "vote": null
     },
     "iq_by_action": {}
    },
    "authors": [
     {
      "attribution": 0.8285714285714286,
      "pinned_role": null,
      "user": {
       "api_path": "/users/9315835",
       "avatar": {
        "tiny": {
         "url": "https://images.genius.com/avatars/tiny/592b05b436c623c31d1abddbca2cfcad",
         "bounding_box": {
          "width": 16,
          "height": 16
         }
        },
        "thumb": {
         "url": "https://images.genius.com/avatars/thumb/592b05b436c623c31d1abddbca2cfcad",
         "bounding_box": {
          "width": 32,
          "height": 32
         }
        },
        "small": {
         "url": "https://images.genius.com/avatars/small/592b05b436c623c31d1abddbca2cfcad",
         "bounding_box": {
          "width": 100,
          "height": 100
         }
        },
        "medium": {
         "url": "https://images.genius.com/avatars/medium/592b05b436c623c31d1abddbca2cfcad",
         "bounding_box": {
          "width": 300,
          "height": 400
         }
        }
       },
       "header_image_url": "https://s3.amazonaws.com/filepicker-images-rapgenius/fe43cnws3c",
       "human_readable_role_for_display": "Contributor",
       "id": 9315835,
       "iq": 12343,
       "login": "Crystallisee",
       "name": "Crystallisee",
       "role_for_display": "contributor",
       "url": "https://genius.com/Crystallisee",
       "current_user_metadata": {
        "permissions": [],
        "excluded_permissions": [
         "follow"
        ],
        "interactions": {
         "following": false
        }
       }
      }
     },
     {
      "attribution": 0.17142857142857143,
      "pinned_role": null,
      "user": {
       "api_path": "/users/12728595",
       "avatar": {
        "tiny": {
         "url": "https://images.genius.com/avatars/tiny/75302393de5f5803cb6f8a5ea7e9f5a1",
         "bounding_box": {
          "width": 16,
          "height": 16
         }
        },
        "thumb": {
         "url": "https://images.genius.com/avatars/thumb/75302393de5f5803cb6f8a5ea7e9f5a1",
         "bounding_box": {
          "width": 32,
          "height": 32
         }
        },
        "small": {
         "url": "https://images.genius.com/avatars/small/75302393de5f5803cb6f8a5ea7e9f5a1",
         "bounding_box": {
          "width": 100,
          "height": 100
         }
        },
        "medium": {
         "url": "https://images.genius.com/avatars/medium/75302393de5f5803cb6f8a5ea7e9f5a1",
         "bounding_box": {
          "width": 300,
          "height": 400
         }
        }
       },
       "header_image_url": "https://s3.amazonaws.com/filepicker-images-rapgenius/yg7l66wj8u",
       "human_readable_role_for_display": "Contributor",
       "id": 12728595,
       "iq": 1731,
       "login": "lilcalmusic",
       "name": "lilcalmusic",
       "role_for_display": "contributor",
       "url": "https://genius.com/lilcalmusic",
       "current_user_metadata": {
        "permissions": [],
        "excluded_permissions": [
         "follow"
        ],
        "interactions": {
         "following": false
        }
       }
      }
     }
    ],
    "cosigned_by": [],
    "rejection_comment": null,
    "verified_by": null
   }
  ]
 },
 "user": null,
 "songs": [
  {
   "annotation_count": 1,
   "api_path": "/songs/5925827",
   "artist_names": "NextYoungin",
   "full_title": "Young Boss Anthem by\u00a0NextYoungin",
   "header_image_thumbnail_url": "https://images.genius.com/95b836ae4a6f6e808408bd0e9d12f1c1.216x120x1.jpg",
   "header_image_url": "https://images.genius.com/95b836ae4a6f6e808408bd0e9d12f1c1.216x120x1.jpg",
   "id": 5925827,
   "language": "en",
   "lyrics_owner_id": 8431141,
   "lyrics_state": "complete",
   "path": "/Nextyoungin-young-boss-anthem-lyrics",
   "pyongs_count": null,
   "relationships_index_url": "https://genius.com/Nextyoungin-young-boss-anthem-sample",
   "release_date_components": {
    "year": 2020,
    "month": 9,
    "day": 19
   },
   "release_date_for_display": "September 19, 2020",
   "release_date_with_abbreviated_month_for_display": "Sep. 19, 2020",
   "song_art_image_thumbnail_url": "https://images.genius.com/c63bda2510a8e485848c996aa3118d3b.300x300x1.jpg",
   "song_art_image_url": "https://images.genius.com/c63bda2510a8e485848c996aa3118d3b.1000x1000x1.jpg",
   "stats": {
    "accepted_annotations": 1,
    "contributors": 5,
    "iq_earners": 5,
    "transcribers": 2,
    "unreviewed_annotations": 0,
    "verified_annotations": 0,
    "hot": false
   },
   "title": "Young Boss Anthem",
   "title_with_featured": "Young Boss Anthem",
   "url": "https://genius.com/Nextyoungin-young-boss-anthem-lyrics",
   "featured_artists": [],
   "primary_artist": {
    "api_path": "/artists/2287247",
    "header_image_url": "https://images.genius.com/7f57042cb7726dd74f9550e3823dd999.670x1000x1.jpg",
    "id": 2287247,
    "image_url": "https://images.genius.com/d383eeb0f6f77a9b9a2ea3236dbbadae.285x285x1.jpg",
    "is_meme_verified": false,
    "is_verified": false,
    "name": "NextYoungin",
    "url": "https://genius.com/artists/Nextyoungin"
   },
   "apple_music_id": "1531788267",
   "apple_music_player_url": "https://genius.com/songs/5925827/apple_music_player",
   "description": {
    "plain": "?"
   },
   "embed_content": "<div id='rg_embed_link_5925827' class='rg_embed_link' data-song-id='5925827'>Read <a href='https://genius.com/Nextyoungin-young-boss-anthem-lyrics'>\u201cYoung Boss Anthem\u201d by NextYoungin</a> on Genius</div> <script crossorigin src='//genius.com/songs/5925827/embed.js'></script>",
   "featured_video": false,
   "lyrics_placeholder_reason": null,
   "recording_location": null,
   "release_date": "2020-09-19",
   "current_user_metadata": {
    "permissions": [
     "view_apple_music_player",
     "view_recommendations",
     "view_song_story_gallery"
    ],
    "excluded_permissions": [
     "follow",
     "award_transcription_iq",
     "remove_transcription_iq",
     "see_pageviews",
     "pyong",
     "edit_lyrics",
     "view_annotation_engagement_data",
     "publish",
     "unpublish",
     "edit_spotify_details",
     "hide",
     "unhide",
     "toggle_featured_video",
     "add_pinned_annotation_to",
     "add_community_annotation_to",
     "destroy",
     "mark_as_not_spam",
     "edit_spotify_annotations_for",
     "verify_lyrics",
     "unverify_lyrics",
     "edit_anything",
     "edit_any_media",
     "edit",
     "rename",
     "edit_tags",
     "reindex",
     "view_lyrics_synchronization",
     "enable_media",
     "disable_media",
     "edit_lyrics_or_annotation_brackets",
     "see_editorial_indicators",
     "view_attribution_visualization",
     "edit_annotation_brackets",
     "preview_lyrics_for_export",
     "hide_apple_player",
     "unhide_apple_player",
     "trigger_apple_match",
     "mark_lyrics_evaluation_as_complete",
     "mark_lyrics_evaluation_as_staff_approved",
     "unmark_lyrics_evaluation_as_complete",
     "mark_lyrics_evaluation_as_un_staff_approved",
     "view_transcriber_media_player",
     "override_apple_match",
     "set_song_color_gradient",
     "mark_as_hot",
     "unmark_as_hot",
     "view_relationships_page",
     "edit_youtube_url",
     "edit_soundcloud_url",
     "edit_spotify_uuid",
     "edit_vevo_url",
     "create_comment",
     "moderate_annotations",
     "create_annotation",
     "see_short_id",
     "manage_chart_item",
     "create_tag",
     "propose_lyrics_edit",
     "view_lyrics_edit_proposals_on_song",
     "create_question"
    ],
    "interactions": {
     "pyong": false,
     "following": false
    },
    "relationships": {},
    "iq_by_action": {}
   },
   "album": {
    "api_path": "/albums/687925",
    "cover_art_url": "https://assets.genius.com/images/default_cover_art.png?1682450960",
    "full_title": "NY1* by NextYoungin",
    "id": 687925,
    "name": "NY1*",
    "release_date_for_display": null,
    "url": "https://genius.com/albums/Nextyoungin/Ny1",
    "artist": {
     "api_path": "/artists/2287247",
     "header_image_url": "https://images.genius.com/7f57042cb7726dd74f9550e3823dd999.670x1000x1.jpg",
     "id": 2287247,
     "image_url": "https://images.genius.com/d383eeb0f6f77a9b9a2ea3236dbbadae.285x285x1.jpg",
     "is_meme_verified": false,
     "is_verified": false,
     "name": "NextYoungin",
     "url": "https://genius.com/artists/Nextyoungin"
    }
   },
   "custom_performances": [
    {
     "label": "Cover Art Design",
     "artists": [
      {
       "api_path": "/artists/2381107",
       "header_image_url": "https://images.genius.com/ece0a246e166a34d5f23d83d60bf5cf7.894x894x1.jpg",
       "id": 2381107,
       "image_url": "https://images.genius.com/ece0a246e166a34d5f23d83d60bf5cf7.894x894x1.jpg",
       "is_meme_verified": false,
       "is_verified": false,
       "name": "Makuchuu",
       "url": "https://genius.com/artists/Makuchuu"
      }
     ]
    },
    {
     "label": "Mixing Engineer",
     "artists": [
      {
       "api_path": "/artists/2229610",
       "header_image_url": "https://images.genius.com/dbf06d7ee0663c88fc894018abb34bb5.400x400x1.jpg",
       "id": 2229610,
       "image_url": "https://images.genius.com/dbf06d7ee0663c88fc894018abb34bb5.400x400x1.jpg",
       "is_meme_verified": false,
       "is_verified": false,
       "name": "SpainDaGoat",
       "url": "https://genius.com/artists/Spaindagoat"
      }
     ]
    },
    {
     "label": "Mastering Engneer",
     "artists": [
      {
       "api_path": "/artists/2229610",
       "header_image_url": "https://images.genius.com/dbf06d7ee0663c88fc894018abb34bb5.400x400x1.jpg",
       "id": 2229610,
       "image_url": "https://images.genius.com/dbf06d7ee0663c88fc894018abb34bb5.400x400x1.jpg",
       "is_meme_verified": false,
       "is_verified": false,
       "name": "SpainDaGoat",
       "url": "https://genius.com/artists/Spaindagoat"
      }
     ]
    },
    {
     "label": "Recording Engineer",
     "artists": [
      {
       "api_path": "/artists/2229610",
       "header_image_url": "https://images.genius.com/dbf06d7ee0663c88fc894018abb34bb5.400x400x1.jpg",
       "id": 2229610,
       "image_url": "https://images.genius.com/dbf06d7ee0663c88fc894018abb34bb5.400x400x1.jpg",
       "is_meme_verified": false,
       "is_verified": false,
       "name": "SpainDaGoat",
       "url": "https://genius.com/artists/Spaindagoat"
      }
     ]
    }
   ],
   "description_annotation": {
    "_type": "referent",
    "annotator_id": 8431141,
    "annotator_login": "masterhype",
    "api_path": "/referents/21044530",
    "classification": "needs_exegesis",
    "fragment": "Young Boss Anthem",
    "id": 21044530,
    "is_description": true,
    "path": "/21044530/Nextyoungin-young-boss-anthem/Young-boss-anthem",
    "range": {
     "content": "Young Boss Anthem"
    },
    "song_id": 5925827,
    "url": "https://genius.com/21044530/Nextyoungin-young-boss-anthem/Young-boss-anthem",
    "verified_annotator_ids": [],
    "annotatable": {
     "api_path": "/songs/5925827",
     "client_timestamps": {
      "updated_by_human_at": 1610370855,
      "lyrics_updated_at": 1600490249
     },
     "context": "NextYoungin",
     "id": 5925827,
     "image_url": "https://images.genius.com/c63bda2510a8e485848c996aa3118d3b.1000x1000x1.jpg",
     "link_title": "Young Boss Anthem by\u00a0NextYoungin",
     "title": "Young Boss Anthem",
     "type": "Song",
     "url": "https://genius.com/Nextyoungin-young-boss-anthem-lyrics"
    },
    "annotations": [
     {
      "api_path": "/annotations/21044530",
      "body": {
       "plain": ""
      },
      "comment_count": 0,
      "community": true,
      "custom_preview": null,
      "has_voters": false,
      "id": 21044530,
      "pinned": false,
      "share_url": "https://genius.com/21044530",
      "source": null,
      "state": "needs_exegesis",
      "url": "https://genius.com/21044530/Nextyoungin-young-boss-anthem/Young-boss-anthem",
      "verified": false,
      "votes_total": 0,
      "current_user_metadata": {
       "permissions": [],
       "excluded_permissions": [
        "vote",
        "edit",
        "cosign",
        "uncosign",
        "destroy",
        "accept",
        "reject",
        "see_unreviewed",
        "clear_votes",
        "propose_edit_to",
        "pin_to_profile",
        "unpin_from_profile",
        "update_source",
        "edit_custom_preview",
        "create_comment"
       ],
       "interactions": {
        "cosign": false,
        "pyong": false,
        "vote": null
       },
       "iq_by_action": {}
      },
      "authors": [
       {
        "attribution": 1.0,
        "pinned_role": null,
        "user": {
         "api_path": "/users/8431141",
         "avatar": {
          "tiny": {
           "url": "https://images.genius.com/1b6d02c2c58116c798b7775d433edbea.385x385x1.png",
           "bounding_box": {
            "width": 16,
            "height": 16
           }
          },
          "thumb": {
           "url": "https://images.genius.com/1b6d02c2c58116c798b7775d433edbea.385x385x1.png",
           "bounding_box": {
            "width": 32,
            "height": 32
           }
          },
          "small": {
           "url": "https://images.genius.com/1b6d02c2c58116c798b7775d433edbea.385x385x1.png",
           "bounding_box": {
            "width": 100,
            "height": 100
           }
          },
          "medium": {
           "url": "https://images.genius.com/1b6d02c2c58116c798b7775d433edbea.385x385x1.png",
           "bounding_box": {
            "width": 300,
            "height": 400
           }
          }
         },
         "header_image_url": "https://images.genius.com/8dd274e89282dce4ff4e22c82f03fad2.1000x500x1.png",
         "human_readable_role_for_display": "Editor",
         "id": 8431141,
         "iq": 154143,
         "login": "masterhype",
         "name": "\u200bmasterhype",
         "role_for_display": "editor",
         "url": "https://genius.com/masterhype",
         "current_user_metadata": {
          "permissions": [],
          "excluded_permissions": [
           "follow"
          ],
          "interactions": {
           "following": false
          }
         }
        }
       }
      ],
      "cosigned_by": [],
      "rejection_comment": null,
      "verified_by": null
     }
    ]
   },
   "lyrics_marked_complete_by": null,
   "lyrics_marked_staff_approved_by": null,
   "media": [
    {
     "provider": "youtube",
     "start": 0,
     "type": "video",
     "url": "http://www.youtube.com/watch?v=Z3UiVWVxRU8"
    }
   ],
   "producer_artists": [
    {
     "api_path": "/artists/2229610",
     "header_image_url": "https://images.genius.com/dbf06d7ee0663c88fc894018abb34bb5.400x400x1.jpg",
     "id": 2229610,
     "image_url": "https://images.genius.com/dbf06d7ee0663c88fc894018abb34bb5.400x400x1.jpg",
     "is_meme_verified": false,
     "is_verified": false,
     "name": "SpainDaGoat",
     "url": "https://genius.com/artists/Spaindagoat"
    }
   ],
   "song_relationships": [
    {
     "relationship_type": "samples",
     "type": "samples",
     "songs": []
    },
    {
     "relationship_type": "sampled_in",
     "type": "sampled_in",
     "songs": []
    },
    {
     "relationship_type": "interpolates",
     "type": "interpolates",
     "songs": []
    },
    {
     "relationship_type": "interpolated_by",
     "type": "interpolated_by",
     "songs": []
    },
    {
     "relationship_type": "cover_of",
     "type": "cover_of",
     "songs": []
    },
    {
     "relationship_type": "covered_by",
     "type": "covered_by",
     "songs": []
    },
    {
     "relationship_type": "remix_of",
     "type": "remix_of",
     "songs": []
    },
    {
     "relationship_type": "remixed_by",
     "type": "remixed_by",
     "songs": []
    },
    {
     "relationship_type": "live_version_of",
     "type": "live_version_of",
     "songs": []
    },
    {
     "relationship_type": "performed_live_as",
     "type": "performed_live_as",
     "songs": []
    },
    {
     "relationship_type": "translation_of",
     "type": "translation_of",
     "songs": []
    },
    {
     "relationship_type": "translations",
     "type": "translations",
     "songs": []
    }
   ],
   "translation_songs": [],
   "verified_annotations_by": [],
   "verified_contributors": [],
   "verified_lyrics_by": [],
   "writer_artists": [
    {
     "api_path": "/artists/2287247",
     "header_image_url": "https://images.genius.com/7f57042cb7726dd74f9550e3823dd999.670x1000x1.jpg",
     "id": 2287247,
     "image_url": "https://images.genius.com/d383eeb0f6f77a9b9a2ea3236dbbadae.285x285x1.jpg",
     "is_meme_verified": false,
     "is_verified": false,
     "name": "NextYoungin",
     "url": "https://genius.com/artists/Nextyoungin"
    }
   ],
   "artist": "NextYoungin",
   "lyrics": "5 ContributorsYoung Boss Anthem Lyrics[Intro]\nAyy, ayy\nAyy\nAyy\nShake that ass, lemme see some'\n(Spain what you doin'?)\nBitch, bitch, bitch, bitch, ayy\n\n[Chorus]\nTurn around, shake that ass\nLemme see some' (Lemme see some')\nShe tipsy off the drank, sippin' hella rum (Gang, gang)\nThis the young boss anthem, go hella dumb (Yeah)\nSmack her ass, left cheek, go hella numb\nGo, go, lemme see some'\nGo, go, lemme see some'\nOoh-ayy, okay, lemme see some'\nShorty lookin' good in the party\nLemme beat some', ayy (Ayy, ayy, ayy)\n\n[Verse 1]\nBitch, I'm in the party with the gang (With the gang)\nSmokin' gas, yeah, we smokin' propane (Woo, woo)\nShe throwin' ass hella hard, but I can tame (Woo)\nSorry, baby, I'on even know your name (Know your name)\nFuck your set, give no fuck 'bout what you do (Woo)\nWhere the hoes ain't worried 'bout a nigga in the room (Baow, baow)\nClap, clap, clap, she shake it fast like zoom (Gang)\nDamn, what's your number?\nI'm tryna get up in there soon (In there soon)\nShe suck me up, I might call that bitch Dracula (Ayy)\nHe get cut if a nigga start actin' tough\nNo Game Of Thrones but you know we get the dragon stuff\nI'on gang bang but you know I'm stackin' up\nI'm finna spazz, bitch, I need to smoke some Reefer (Ooh)\nBooty hella big, lil' baby look like a keeper\nThick thighs chokin', shorty put me in a sleeper\nThis not The Night Is Below, baby, hit my beeper (On the gang)\nYou might also like[Chorus]\nTurn around, shake that ass\nLemme see some' (Lemme see some')\nShe tipsy off the drank, sippin' hella rum (Gang, gang)\nThis the young boss anthem, go hella dumb (Yeah)\nSmack her ass, left cheek, go hella numb\nGo, go, lemme see some'\nGo, go, lemme see some'\nOoh-ayy, okay, lemme see some'\nShorty lookin' good in the party\nLemme beat some', ayy (Ayy, ayy, ayy)\n\n[Verse 2]\nAyy, fuck these niggas talkin' 'bout?\nYo' bitch pullin' up to my show whenever I call her now\nShoot my shot at that lil' bitch, mm, guess I'm a baller now\nCaught the bitch eye at the party, damn, she my stalker now\n\n[Bridge]\nOoh-ayy, okay, okay\nI'm 'bout my chips like Frito Lay\nDon't give a fuck what a bitch gotta say\nBitch, don't talk, just shake that thang\nOoh-ayy, okay, okay\nI'm 'bout my chips like Frito Lay\nDon't give a fuck what a bitch gotta say\nBitch, don't talk, just shake that thang\n[Chorus]\nTurn around, shake that ass\nLemme see some' (Lemme see some')\nShe tipsy off the drank, sippin' hella rum (Gang, gang)\nThis the young boss anthem, go hella dumb\nSmack her ass, left cheek, go hella numb\nGo, go, lemme see some'\nGo, go, lemme see some'\nOoh-ayy, okay, lemme see some'\nShorty lookin' good in the party\nLemme beat some', ayy\n\n[Outro]\nOkay, okay\nLike Frito Lay\nWhat a bitch gotta say?\n(Spain what you doin'?)\nJust shake that thangEmbed"
  },
  {
   "annotation_count": 0,
   "api_path": "/songs/6052248",
   "artist_names": "NextYoungin",
   "full_title": "Daddy Kaine by\u00a0NextYoungin",
   "header_image_thumbnail_url": "https://images.genius.com/60eb8c0770df71f3f783fa1b33c2d4fa.300x300x1.png",
   "header_image_url": "https://images.genius.com/60eb8c0770df71f3f783fa1b33c2d4fa.640x640x1.png",
   "id": 6052248,
   "language": "en",
   "lyrics_owner_id": 8431141,
   "lyrics_state": "complete",
   "path": "/Nextyoungin-daddy-kaine-lyrics",
   "pyongs_count": 1,
   "relationships_index_url": "https://genius.com/Nextyoungin-daddy-kaine-sample",
   "release_date_components": {
    "year": 2020,
    "month": 11,
    "day": 12
   },
   "release_date_for_display": "November 12, 2020",
   "release_date_with_abbreviated_month_for_display": "Nov. 12, 2020",
   "song_art_image_thumbnail_url": "https://images.genius.com/60eb8c0770df71f3f783fa1b33c2d4fa.300x300x1.png",
   "song_art_image_url": "https://images.genius.com/60eb8c0770df71f3f783fa1b33c2d4fa.640x640x1.png",
   "stats": {
    "accepted_annotations": 0,
    "contributors": 4,
    "iq_earners": 4,
    "transcribers": 2,
    "unreviewed_annotations": 0,
    "verified_annotations": 0,
    "hot": false
   },
   "title": "Daddy Kaine",
   "title_with_featured": "Daddy Kaine",
   "url": "https://genius.com/Nextyoungin-daddy-kaine-lyrics",
   "featured_artists": [],
   "primary_artist": {
    "api_path": "/artists/2287247",
    "header_image_url": "https://images.genius.com/7f57042cb7726dd74f9550e3823dd999.670x1000x1.jpg",
    "id": 2287247,
    "image_url": "https://images.genius.com/d383eeb0f6f77a9b9a2ea3236dbbadae.285x285x1.jpg",
    "is_meme_verified": false,
    "is_verified": false,
    "name": "NextYoungin",
    "url": "https://genius.com/artists/Nextyoungin"
   },
   "apple_music_id": "1539755696",
   "apple_music_player_url": "https://genius.com/songs/6052248/apple_music_player",
   "description": {
    "plain": "?"
   },
   "embed_content": "<div id='rg_embed_link_6052248' class='rg_embed_link' data-song-id='6052248'>Read <a href='https://genius.com/Nextyoungin-daddy-kaine-lyrics'>\u201cDaddy Kaine\u201d by NextYoungin</a> on Genius</div> <script crossorigin src='//genius.com/songs/6052248/embed.js'></script>",
   "featured_video": false,
   "lyrics_placeholder_reason": null,
   "recording_location": null,
   "release_date": "2020-11-12",
   "current_user_metadata": {
    "permissions": [
     "view_apple_music_player",
     "view_recommendations",
     "view_song_story_gallery"
    ],
    "excluded_permissions": [
     "follow",
     "award_transcription_iq",
     "remove_transcription_iq",
     "see_pageviews",
     "pyong",
     "edit_lyrics",
     "view_annotation_engagement_data",
     "publish",
     "unpublish",
     "edit_spotify_details",
     "hide",
     "unhide",
     "toggle_featured_video",
     "add_pinned_annotation_to",
     "add_community_annotation_to",
     "destroy",
     "mark_as_not_spam",
     "edit_spotify_annotations_for",
     "verify_lyrics",
     "unverify_lyrics",
     "edit_anything",
     "edit_any_media",
     "edit",
     "rename",
     "edit_tags",
     "reindex",
     "view_lyrics_synchronization",
     "enable_media",
     "disable_media",
     "edit_lyrics_or_annotation_brackets",
     "see_editorial_indicators",
     "view_attribution_visualization",
     "edit_annotation_brackets",
     "preview_lyrics_for_export",
     "hide_apple_player",
     "unhide_apple_player",
     "trigger_apple_match",
     "mark_lyrics_evaluation_as_complete",
     "mark_lyrics_evaluation_as_staff_approved",
     "unmark_lyrics_evaluation_as_complete",
     "mark_lyrics_evaluation_as_un_staff_approved",
     "view_transcriber_media_player",
     "override_apple_match",
     "set_song_color_gradient",
     "mark_as_hot",
     "unmark_as_hot",
     "view_relationships_page",
     "edit_youtube_url",
     "edit_soundcloud_url",
     "edit_spotify_uuid",
     "edit_vevo_url",
     "create_comment",
     "moderate_annotations",
     "create_annotation",
     "see_short_id",
     "manage_chart_item",
     "create_tag",
     "propose_lyrics_edit",
     "view_lyrics_edit_proposals_on_song",
     "create_question"
    ],
    "interactions": {
     "pyong": false,
     "following": false
    },
    "relationships": {},
    "iq_by_action": {}
   },
   "album": {
    "api_path": "/albums/687925",
    "cover_art_url": "https://assets.genius.com/images/default_cover_art.png?1682450960",
    "full_title": "NY1* by NextYoungin",
    "id": 687925,
    "name": "NY1*",
    "release_date_for_display": null,
    "url": "https://genius.com/albums/Nextyoungin/Ny1",
    "artist": {
     "api_path": "/artists/2287247",
     "header_image_url": "https://images.genius.com/7f57042cb7726dd74f9550e3823dd999.670x1000x1.jpg",
     "id": 2287247,
     "image_url": "https://images.genius.com/d383eeb0f6f77a9b9a2ea3236dbbadae.285x285x1.jpg",
     "is_meme_verified": false,
     "is_verified": false,
     "name": "NextYoungin",
     "url": "https://genius.com/artists/Nextyoungin"
    }
   },
   "custom_performances": [],
   "description_annotation": {
    "_type": "referent",
    "annotator_id": 8431141,
    "annotator_login": "masterhype",
    "api_path": "/referents/21656924",
    "classification": "needs_exegesis",
    "fragment": "Daddy Kaine",
    "id": 21656924,
    "is_description": true,
    "path": "/21656924/Nextyoungin-daddy-kaine/Daddy-kaine",
    "range": {
     "content": "Daddy Kaine"
    },
    "song_id": 6052248,
    "url": "https://genius.com/21656924/Nextyoungin-daddy-kaine/Daddy-kaine",
    "verified_annotator_ids": [],
    "annotatable": {
     "api_path": "/songs/6052248",
     "client_timestamps": {
      "updated_by_human_at": 1608417480,
      "lyrics_updated_at": 1608417459
     },
     "context": "NextYoungin",
     "id": 6052248,
     "image_url": "https://images.genius.com/60eb8c0770df71f3f783fa1b33c2d4fa.640x640x1.png",
     "link_title": "Daddy Kaine by\u00a0NextYoungin",
     "title": "Daddy Kaine",
     "type": "Song",
     "url": "https://genius.com/Nextyoungin-daddy-kaine-lyrics"
    },
    "annotations": [
     {
      "api_path": "/annotations/21656924",
      "body": {
       "plain": ""
      },
      "comment_count": 0,
      "community": true,
      "custom_preview": null,
      "has_voters": false,
      "id": 21656924,
      "pinned": false,
      "share_url": "https://genius.com/21656924",
      "source": null,
      "state": "needs_exegesis",
      "url": "https://genius.com/21656924/Nextyoungin-daddy-kaine/Daddy-kaine",
      "verified": false,
      "votes_total": 0,
      "current_user_metadata": {
       "permissions": [],
       "excluded_permissions": [
        "vote",
        "edit",
        "cosign",
        "uncosign",
        "destroy",
        "accept",
        "reject",
        "see_unreviewed",
        "clear_votes",
        "propose_edit_to",
        "pin_to_profile",
        "unpin_from_profile",
        "update_source",
        "edit_custom_preview",
        "create_comment"
       ],
       "interactions": {
        "cosign": false,
        "pyong": false,
        "vote": null
       },
       "iq_by_action": {}
      },
      "authors": [
       {
        "attribution": 1.0,
        "pinned_role": null,
        "user": {
         "api_path": "/users/8431141",
         "avatar": {
          "tiny": {
           "url": "https://images.genius.com/1b6d02c2c58116c798b7775d433edbea.385x385x1.png",
           "bounding_box": {
            "width": 16,
            "height": 16
           }
          },
          "thumb": {
           "url": "https://images.genius.com/1b6d02c2c58116c798b7775d433edbea.385x385x1.png",
           "bounding_box": {
            "width": 32,
            "height": 32
           }
          },
          "small": {
           "url": "https://images.genius.com/1b6d02c2c58116c798b7775d433edbea.385x385x1.png",
           "bounding_box": {
            "width": 100,
            "height": 100
           }
          },
          "medium": {
           "url": "https://images.genius.com/1b6d02c2c58116c798b7775d433edbea.385x385x1.png",
           "bounding_box": {
            "width": 300,
            "height": 400
           }
          }
         },
         "header_image_url": "https://images.genius.com/8dd274e89282dce4ff4e22c82f03fad2.1000x500x1.png",
         "human_readable_role_for_display": "Editor",
         "id": 8431141,
         "iq": 154143,
         "login": "masterhype",
         "name": "\u200bmasterhype",
         "role_for_display": "editor",
         "url": "https://genius.com/masterhype",
         "current_user_metadata": {
          "permissions": [],
          "excluded_permissions": [
           "follow"
          ],
          "interactions": {
           "following": false
          }
         }
        }
       }
      ],
      "cosigned_by": [],
      "rejection_comment": null,
      "verified_by": null
     }
    ]
   },
   "lyrics_marked_complete_by": null,
   "lyrics_marked_staff_approved_by": null,
   "media": [
    {
     "provider": "youtube",
     "start": 0,
     "type": "video",
     "url": "http://www.youtube.com/watch?v=lF9P2-kXf8k"
    }
   ],
   "producer_artists": [
    {
     "api_path": "/artists/2229610",
     "header_image_url": "https://images.genius.com/dbf06d7ee0663c88fc894018abb34bb5.400x400x1.jpg",
     "id": 2229610,
     "image_url": "https://images.genius.com/dbf06d7ee0663c88fc894018abb34bb5.400x400x1.jpg",
     "is_meme_verified": false,
     "is_verified": false,
     "name": "SpainDaGoat",
     "url": "https://genius.com/artists/Spaindagoat"
    }
   ],
   "song_relationships": [
    {
     "relationship_type": "samples",
     "type": "samples",
     "songs": []
    },
    {
     "relationship_type": "sampled_in",
     "type": "sampled_in",
     "songs": []
    },
    {
     "relationship_type": "interpolates",
     "type": "interpolates",
     "songs": []
    },
    {
     "relationship_type": "interpolated_by",
     "type": "interpolated_by",
     "songs": []
    },
    {
     "relationship_type": "cover_of",
     "type": "cover_of",
     "songs": []
    },
    {
     "relationship_type": "covered_by",
     "type": "covered_by",
     "songs": []
    },
    {
     "relationship_type": "remix_of",
     "type": "remix_of",
     "songs": []
    },
    {
     "relationship_type": "remixed_by",
     "type": "remixed_by",
     "songs": []
    },
    {
     "relationship_type": "live_version_of",
     "type": "live_version_of",
     "songs": []
    },
    {
     "relationship_type": "performed_live_as",
     "type": "performed_live_as",
     "songs": []
    },
    {
     "relationship_type": "translation_of",
     "type": "translation_of",
     "songs": []
    },
    {
     "relationship_type": "translations",
     "type": "translations",
     "songs": []
    }
   ],
   "translation_songs": [],
   "verified_annotations_by": [],
   "verified_contributors": [],
   "verified_lyrics_by": [],
   "writer_artists": [
    {
     "api_path": "/artists/2287247",
     "header_image_url": "https://images.genius.com/7f57042cb7726dd74f9550e3823dd999.670x1000x1.jpg",
     "id": 2287247,
     "image_url": "https://images.genius.com/d383eeb0f6f77a9b9a2ea3236dbbadae.285x285x1.jpg",
     "is_meme_verified": false,
     "is_verified": false,
     "name": "NextYoungin",
     "url": "https://genius.com/artists/Nextyoungin"
    }
   ],
   "artist": "NextYoungin",
   "lyrics": "4 ContributorsDaddy Kaine Lyrics[Intro]\n(Spain, what you doing?)\n\n[Chorus]\nThis that G-Model 6, she let me hit when pigs fly\nSo I put a cop on a plane\nThis bitch trippin' on me, I'on know why (Huh)\nHo, you not even my main\nI'm rockin Louis V, Balmain\nI leave a opp wet up in the rain\nToo many bitches feel like Daddy Kaine (Let's go)\nBob The Builder, I hit you with a crane\n\n[Verse 1]\nGot a bag on you niggas, what's up? (Lil bitch)\nI got nothing but Runtz in my blunt (Swoo)\nHe say he got muddy in his cup\nBut I found out that it was the tuss (no cap)\nHe see us and the envy come up\nFinna hop out the Bentley truck (skirt skirt)\nInterior white, don't fuck this shit up\nShe lick it up so good it make me cuss, fuck\n\n[Post-Chorus]\nGotta run it up (Uh)\nBig boss moves, can't fuck it up (Uh)\nIn the strip club, might chuck it up\nBought her a new ass, now she got double butt\nI made to drip in Amiri\nLaugh at yo fit you so silly, I'm finna rack up a milli'\nI might hit you with this ray, I'm not talkin' Billy\nThat lil' bitch w\u0435t no willy\nYou might also like[Verse 2]\nI got treasure on my neck feel lik\u0435 Nicolas Cage\nSaid she don\u2019t know me but she stalking my page\nGot this nigga wife stripping up in my bedroom and just like a gamer, he rage (Haha)\nLook at me I made a way (Let's get it)\nHad to push some people out the way (No cap)\nThese niggas be tryna stay (Let's go)\nSix feet under, that\u2019s where you gone lay\n\n[Chorus]\nThis that G-Model 6, she let me hit when pigs fly\nSo I put a cop on a plane\nThis bitch trippin' on me, I'on know why (Huh)\nHo, you not even my main\nI'm rockin Louis V, Balmain\nI leave a opp wet up in the rain\nToo many bitches feel like Daddy Kaine (Let's go)\nBob The Builder, I hit you with a crane\nThis that G-Model 6, she let me hit when pigs fly\nSo I put a cop on a plane\nThis bitch trippin' on me, I'on know why (Huh)\nHo, you not even my main\nI'm rockin Louis V, Balmain\nI leave a opp wet up in the rain\nToo many bitches feel like Daddy Kaine (Let's go)\nBob The Builder, I hit you with a crane (Woo)\n[Verse 3]\nRockin' the two tone\nNiggas be clueless, yeah, they stuck in a loop hole\nYou little like a flute hole (Uh)\nMove ho, but you made it this far, nigga, I give you kudos (Uh)\nI just don't understand how a motherfucker like me ain't put a beam on ya face\nYou a disgrace, don\u2019t slip up, nigga, there's a time and the place\nMy niggas they ready, they finna catch this case\nBullet sum' like a cat it\u2019ll scratch your face\nSpray just like mace, shit\nI need some space, gotta get away from the whole human race\n'Cause niggas be plastic, I know that they fake\nBut I\u2019m livin good, I got steak on my plate\n'Cause niggas be plastic, I know that they fake\nBut I'm livin good, I got steak on my plate, lil' bitch\n\n[Outro]\nLil' bitch\n(Spain, what you doing?)1Embed"
  },
  {
   "annotation_count": 0,
   "api_path": "/songs/8346595",
   "artist_names": "NextYoungin",
   "full_title": "Pop Yo Shi Twin by\u00a0NextYoungin",
   "header_image_thumbnail_url": "https://images.genius.com/9076cc7541449caa58f1bbf49454047f.300x300x1.png",
   "header_image_url": "https://images.genius.com/9076cc7541449caa58f1bbf49454047f.1000x1000x1.png",
   "id": 8346595,
   "language": "en",
   "lyrics_owner_id": 2510448,
   "lyrics_state": "complete",
   "path": "/Nextyoungin-pop-yo-shi-twin-lyrics",
   "pyongs_count": null,
   "relationships_index_url": "https://genius.com/Nextyoungin-pop-yo-shi-twin-sample",
   "release_date_components": {
    "year": 2022,
    "month": 9,
    "day": 1
   },
   "release_date_for_display": "September 1, 2022",
   "release_date_with_abbreviated_month_for_display": "Sep. 1, 2022",
   "song_art_image_thumbnail_url": "https://images.genius.com/9076cc7541449caa58f1bbf49454047f.300x300x1.png",
   "song_art_image_url": "https://images.genius.com/9076cc7541449caa58f1bbf49454047f.1000x1000x1.png",
   "stats": {
    "accepted_annotations": 0,
    "contributors": 2,
    "iq_earners": 2,
    "transcribers": 1,
    "unreviewed_annotations": 0,
    "verified_annotations": 0,
    "hot": false
   },
   "title": "Pop Yo Shi Twin",
   "title_with_featured": "Pop Yo Shi Twin",
   "url": "https://genius.com/Nextyoungin-pop-yo-shi-twin-lyrics",
   "featured_artists": [],
   "primary_artist": {
    "api_path": "/artists/2287247",
    "header_image_url": "https://images.genius.com/7f57042cb7726dd74f9550e3823dd999.670x1000x1.jpg",
    "id": 2287247,
    "image_url": "https://images.genius.com/d383eeb0f6f77a9b9a2ea3236dbbadae.285x285x1.jpg",
    "is_meme_verified": false,
    "is_verified": false,
    "name": "NextYoungin",
    "url": "https://genius.com/artists/Nextyoungin"
   },
   "apple_music_id": "1641345269",
   "apple_music_player_url": "https://genius.com/songs/8346595/apple_music_player",
   "description": {
    "plain": "?"
   },
   "embed_content": "<div id='rg_embed_link_8346595' class='rg_embed_link' data-song-id='8346595'>Read <a href='https://genius.com/Nextyoungin-pop-yo-shi-twin-lyrics'>\u201cPop Yo Shi Twin\u201d by NextYoungin</a> on Genius</div> <script crossorigin src='//genius.com/songs/8346595/embed.js'></script>",
   "featured_video": false,
   "lyrics_placeholder_reason": null,
   "recording_location": null,
   "release_date": "2022-09-01",
   "current_user_metadata": {
    "permissions": [
     "view_apple_music_player",
     "view_recommendations",
     "view_song_story_gallery"
    ],
    "excluded_permissions": [
     "follow",
     "award_transcription_iq",
     "remove_transcription_iq",
     "see_pageviews",
     "pyong",
     "edit_lyrics",
     "view_annotation_engagement_data",
     "publish",
     "unpublish",
     "edit_spotify_details",
     "hide",
     "unhide",
     "toggle_featured_video",
     "add_pinned_annotation_to",
     "add_community_annotation_to",
     "destroy",
     "mark_as_not_spam",
     "edit_spotify_annotations_for",
     "verify_lyrics",
     "unverify_lyrics",
     "edit_anything",
     "edit_any_media",
     "edit",
     "rename",
     "edit_tags",
     "reindex",
     "view_lyrics_synchronization",
     "enable_media",
     "disable_media",
     "edit_lyrics_or_annotation_brackets",
     "see_editorial_indicators",
     "view_attribution_visualization",
     "edit_annotation_brackets",
     "preview_lyrics_for_export",
     "hide_apple_player",
     "unhide_apple_player",
     "trigger_apple_match",
     "mark_lyrics_evaluation_as_complete",
     "mark_lyrics_evaluation_as_staff_approved",
     "unmark_lyrics_evaluation_as_complete",
     "mark_lyrics_evaluation_as_un_staff_approved",
     "view_transcriber_media_player",
     "override_apple_match",
     "set_song_color_gradient",
     "mark_as_hot",
     "unmark_as_hot",
     "view_relationships_page",
     "edit_youtube_url",
     "edit_soundcloud_url",
     "edit_spotify_uuid",
     "edit_vevo_url",
     "create_comment",
     "moderate_annotations",
     "create_annotation",
     "see_short_id",
     "manage_chart_item",
     "create_tag",
     "propose_lyrics_edit",
     "view_lyrics_edit_proposals_on_song",
     "create_question"
    ],
    "interactions": {
     "pyong": false,
     "following": false
    },
    "relationships": {},
    "iq_by_action": {}
   },
   "album": null,
   "custom_performances": [],
   "description_annotation": {
    "_type": "referent",
    "annotator_id": 2510448,
    "annotator_login": "ohhyeahh",
    "api_path": "/referents/26621528",
    "classification": "needs_exegesis",
    "fragment": "Pop Yo Shi Twin",
    "id": 26621528,
    "is_description": true,
    "path": "/26621528/Nextyoungin-pop-yo-shi-twin/Pop-yo-shi-twin",
    "range": {
     "content": "Pop Yo Shi Twin"
    },
    "song_id": 8346595,
    "url": "https://genius.com/26621528/Nextyoungin-pop-yo-shi-twin/Pop-yo-shi-twin",
    "verified_annotator_ids": [],
    "annotatable": {
     "api_path": "/songs/8346595",
     "client_timestamps": {
      "updated_by_human_at": 1666396034,
      "lyrics_updated_at": 1662051874
     },
     "context": "NextYoungin",
     "id": 8346595,
     "image_url": "https://images.genius.com/9076cc7541449caa58f1bbf49454047f.1000x1000x1.png",
     "link_title": "Pop Yo Shi Twin by\u00a0NextYoungin",
     "title": "Pop Yo Shi Twin",
     "type": "Song",
     "url": "https://genius.com/Nextyoungin-pop-yo-shi-twin-lyrics"
    },
    "annotations": [
     {
      "api_path": "/annotations/26621528",
      "body": {
       "plain": ""
      },
      "comment_count": 0,
      "community": true,
      "custom_preview": null,
      "has_voters": false,
      "id": 26621528,
      "pinned": false,
      "share_url": "https://genius.com/26621528",
      "source": null,
      "state": "needs_exegesis",
      "url": "https://genius.com/26621528/Nextyoungin-pop-yo-shi-twin/Pop-yo-shi-twin",
      "verified": false,
      "votes_total": 0,
      "current_user_metadata": {
       "permissions": [],
       "excluded_permissions": [
        "vote",
        "edit",
        "cosign",
        "uncosign",
        "destroy",
        "accept",
        "reject",
        "see_unreviewed",
        "clear_votes",
        "propose_edit_to",
        "pin_to_profile",
        "unpin_from_profile",
        "update_source",
        "edit_custom_preview",
        "create_comment"
       ],
       "interactions": {
        "cosign": false,
        "pyong": false,
        "vote": null
       },
       "iq_by_action": {}
      },
      "authors": [
       {
        "attribution": 1.0,
        "pinned_role": null,
        "user": {
         "api_path": "/users/2510448",
         "avatar": {
          "tiny": {
           "url": "https://images.genius.com/avatars/tiny/49e8413d8dde10290cc8e732e69f7d90",
           "bounding_box": {
            "width": 16,
            "height": 16
           }
          },
          "thumb": {
           "url": "https://images.genius.com/avatars/thumb/49e8413d8dde10290cc8e732e69f7d90",
           "bounding_box": {
            "width": 32,
            "height": 32
           }
          },
          "small": {
           "url": "https://images.genius.com/avatars/small/49e8413d8dde10290cc8e732e69f7d90",
           "bounding_box": {
            "width": 100,
            "height": 100
           }
          },
          "medium": {
           "url": "https://images.genius.com/avatars/medium/49e8413d8dde10290cc8e732e69f7d90",
           "bounding_box": {
            "width": 300,
            "height": 400
           }
          }
         },
         "header_image_url": "https://images.genius.com/avatars/medium/49e8413d8dde10290cc8e732e69f7d90",
         "human_readable_role_for_display": "Contributor",
         "id": 2510448,
         "iq": 3737,
         "login": "ohhyeahh",
         "name": "ohhyeahh",
         "role_for_display": "contributor",
         "url": "https://genius.com/ohhyeahh",
         "current_user_metadata": {
          "permissions": [],
          "excluded_permissions": [
           "follow"
          ],
          "interactions": {
           "following": false
          }
         }
        }
       }
      ],
      "cosigned_by": [],
      "rejection_comment": null,
      "verified_by": null
     }
    ]
   },
   "lyrics_marked_complete_by": null,
   "lyrics_marked_staff_approved_by": null,
   "media": [
    {
     "provider": "youtube",
     "start": 0,
     "type": "video",
     "url": "http://www.youtube.com/watch?v=7Hr3gCJKOLc"
    }
   ],
   "producer_artists": [
    {
     "api_path": "/artists/2229610",
     "header_image_url": "https://images.genius.com/dbf06d7ee0663c88fc894018abb34bb5.400x400x1.jpg",
     "id": 2229610,
     "image_url": "https://images.genius.com/dbf06d7ee0663c88fc894018abb34bb5.400x400x1.jpg",
     "is_meme_verified": false,
     "is_verified": false,
     "name": "SpainDaGoat",
     "url": "https://genius.com/artists/Spaindagoat"
    },
    {
     "api_path": "/artists/649",
     "header_image_url": "https://images.genius.com/acbbbdcd6a2e27ef24ee72f1153adac2.999x999x1.jpg",
     "id": 649,
     "image_url": "https://images.genius.com/acbbbdcd6a2e27ef24ee72f1153adac2.999x999x1.jpg",
     "is_meme_verified": false,
     "is_verified": false,
     "name": "D-Lo",
     "url": "https://genius.com/artists/D-lo"
    }
   ],
   "song_relationships": [
    {
     "relationship_type": "samples",
     "type": "samples",
     "songs": []
    },
    {
     "relationship_type": "sampled_in",
     "type": "sampled_in",
     "songs": []
    },
    {
     "relationship_type": "interpolates",
     "type": "interpolates",
     "songs": []
    },
    {
     "relationship_type": "interpolated_by",
     "type": "interpolated_by",
     "songs": []
    },
    {
     "relationship_type": "cover_of",
     "type": "cover_of",
     "songs": []
    },
    {
     "relationship_type": "covered_by",
     "type": "covered_by",
     "songs": []
    },
    {
     "relationship_type": "remix_of",
     "type": "remix_of",
     "songs": []
    },
    {
     "relationship_type": "remixed_by",
     "type": "remixed_by",
     "songs": []
    },
    {
     "relationship_type": "live_version_of",
     "type": "live_version_of",
     "songs": []
    },
    {
     "relationship_type": "performed_live_as",
     "type": "performed_live_as",
     "songs": []
    },
    {
     "relationship_type": "translation_of",
     "type": "translation_of",
     "songs": []
    },
    {
     "relationship_type": "translations",
     "type": "translations",
     "songs": []
    }
   ],
   "translation_songs": [],
   "verified_annotations_by": [],
   "verified_contributors": [],
   "verified_lyrics_by": [],
   "writer_artists": [],
   "artist": "NextYoungin",
   "lyrics": "2 ContributorsPop Yo Shi Twin Lyrics[Intro]\nI\u2019m sick of these lame ass hoes acting like I ain't that bitch for real like\n(they ain\u2019t talking bout nun twin)\n\nWho really lit (who)\nWho put you on to this shit (bitch\u205fwho)\nI\u205fwas\u205fone that they\u205flove when I\u205fwas a stud\nThey love me more now that switch, cuz I\u2019m that bitch\n\n[Hook]\nPop yo shit twin, pop yo shit\nI'm that bitch\nPop yo shit twin, pop yo shit\nI'm that Bitch\nPop yo shit twin, pop yo shit\nIm that Bitch\nPop yo shit twin, pop yo shit\n\n[Verse 1]\nThey copying me (Twinnn)\nThese bitches they know I\u2019m the topic (hey bitch)\nThese niggas they love when I pop it (baddie)\nThese hoes be praying I stop it\nBut they copying me (weirdo)\nAnd that shit don\u2019t make no sense\nNow why would I beef with a basic bitch\nA pussy hoe could never ever take my drip (tha fuck)\nYou might also likeI find it funny how bitches be popping they\nShit when they knowing they got it from me\nI find it funny how niggas be wanting my time\nAnd think they gonna get it for free\n\nStalking my page, they all in my comments\nCuz they was wanna see how I work my lil move\nHoes be thinking I'm wanting they nigga\nI\u2019m like nah bitch I want you cuz I\u2019m that BITCH\n\n[Hook]\nPop yo shit twin, pop yo shit\nI'm that bitch\nPop yo shit twin, pop yo shit\nI'm that Bitch\nPop yo shit twin, pop yo shit\nIm that Bitch\nPop yo shit twin, pop yo shit\n\n[Verse 2]\nI\u2019m breaking the rules huh (no cap)\nThought I was a dude huh (what)\nHe call me a baddie\nBut she call me daddy\nI got em confused huh (haha)\nJohnny Dang on my jewels huh (ice)\nI pull up act a fool huh\nWait this a PSA for any bitch that don\u2019t like me\nHOE DO SUM\nI find it funny how bitches be talking online\nWhen they see me they ask for a pic (groupie)\nI find it funny how niggas had nothin to say\nNow they see me be on all my dick, so tell me\nWho really lit (who)\nWho put you on to this shit (bitch who)\nI was the one that they love when I was a stud\nThey love me more now that i switch cuz IM THAT BITCH\n\n[Hook]\nPop yo shit twin, pop yo shit\nI'm that bitch\nPop yo shit twin, pop yo shit\nI'm that Bitch\nPop yo shit twin, pop yo shit\nIm that Bitch\nPop yo shit twin, pop yo shit\n\n[Outro]\nThey copying meEmbed"
  }
 ]
}